<?xml version="1.0" encoding="Windows-1252" ?>
<!-- *****************************************************************************
Copyright 2010-2013 Ellucian Company L.P. and its affiliates.
 ********************************************************************************* -->
<APPLICANTDATA>
    <GTVLETR>
        <GTVLETR_CODE>E_GIFT</GTVLETR_CODE>
        <GTVLETR_ACTIVITY_DATE>01-JAN-10</GTVLETR_ACTIVITY_DATE>
        <GTVLETR_DUPL_IND>N</GTVLETR_DUPL_IND>
        <GTVLETR_DESC>Event Gift Letter</GTVLETR_DESC>
        <GTVLETR_PRINT_COMMAND/>
        <GTVLETR_LETR_CODE_ALT/>
        <GTVLETR_USER_ID>GRAILS</GTVLETR_USER_ID>
        <GTVLETR_DATA_ORIGIN>GRAILS</GTVLETR_DATA_ORIGIN>
    </GTVLETR>
    <SORELTL>
        <SORELTL_LETR_CODE>E_GIFT</SORELTL_LETR_CODE>
        <SORELTL_ELMT_CODE>EA</SORELTL_ELMT_CODE>
    </SORELTL>
    <GTVLETR>
        <GTVLETR_CODE>E_GIFT_ACK</GTVLETR_CODE>
        <GTVLETR_ACTIVITY_DATE>01-JAN-10</GTVLETR_ACTIVITY_DATE>
        <GTVLETR_DUPL_IND>N</GTVLETR_DUPL_IND>
        <GTVLETR_DESC>Event Gift Letter</GTVLETR_DESC>
        <GTVLETR_PRINT_COMMAND/>
        <GTVLETR_LETR_CODE_ALT/>
        <GTVLETR_USER_ID>GRAILS</GTVLETR_USER_ID>
        <GTVLETR_DATA_ORIGIN>GRAILS</GTVLETR_DATA_ORIGIN>
    </GTVLETR>
    <SORELTL>
        <SORELTL_LETR_CODE>E_GIFT_ACK</SORELTL_LETR_CODE>
        <SORELTL_ELMT_CODE>AS</SORELTL_ELMT_CODE>
    </SORELTL>
    <SARWADF>
        <PROGRAM>BA-ANTHRO</PROGRAM>
        <SARWADF_WAPP_CODE>TE</SARWADF_WAPP_CODE>
        <SARWADF_TERM_CODE_EFF>201410</SARWADF_TERM_CODE_EFF>
        <SARWADF_CURR_RULE>4</SARWADF_CURR_RULE>
        <SARWADF_CURR_RULE_2>5</SARWADF_CURR_RULE_2>
        <SARWADF_SSN_LN_IND>N</SARWADF_SSN_LN_IND>
        <SARWADF_AUTO_APPL_IND>N</SARWADF_AUTO_APPL_IND>
        <SARWADF_AUTO_PUSH_IND>N</SARWADF_AUTO_PUSH_IND>
        <SARWADF_AUTO_RECR_IND>N</SARWADF_AUTO_RECR_IND>
        <SARWADF_AUTO_DEC_IND>N</SARWADF_AUTO_DEC_IND>
        <SARWADF_AUTO_TRAN_IND>N</SARWADF_AUTO_TRAN_IND>
        <SARWADF_ACCEPT_WAIVER_IND>N</SARWADF_ACCEPT_WAIVER_IND>
        <SARWADF_TRAN_MISC_IND>N</SARWADF_TRAN_MISC_IND>
        <SARWADF_ONE_REC_APPL_IND>N</SARWADF_ONE_REC_APPL_IND>
    </SARWADF>

    <SARWAPC>
        <PROGRAM>BA-ANTHRO</PROGRAM>
        <MAJOR>ANTH</MAJOR>
        <SARWAPC_CURR_RULE>4</SARWAPC_CURR_RULE>
        <SARWAPC_CMJR_RULE>397</SARWAPC_CMJR_RULE>
        <SARWAPC_TERM_CODE_EFF>000000</SARWAPC_TERM_CODE_EFF>
        <SARWAPC_WAPP_CODE>CE</SARWAPC_WAPP_CODE>
    </SARWAPC>
    <SOBCURR>
        <PROGRAM>BA</PROGRAM>
        <SOBCURR_CURR_RULE>22</SOBCURR_CURR_RULE>
        <SOBCURR_TERM_CODE_INIT>198010</SOBCURR_TERM_CODE_INIT>
        <SOBCURR_LEVL_CODE>UG</SOBCURR_LEVL_CODE>
        <SOBCURR_ACTIVITY_DATE>01-JAN-10</SOBCURR_ACTIVITY_DATE>
        <SOBCURR_PRIM_ROLL_IND>N</SOBCURR_PRIM_ROLL_IND>
        <SOBCURR_SECD_ROLL_IND>N</SOBCURR_SECD_ROLL_IND>
        <SOBCURR_LOCK_IND>Y</SOBCURR_LOCK_IND>
        <SOBCURR_CAMP_CODE/>
        <SOBCURR_COLL_CODE>AS</SOBCURR_COLL_CODE>
        <SOBCURR_DEGC_CODE>BA</SOBCURR_DEGC_CODE>
        <SOBCURR_PROGRAM>BA</SOBCURR_PROGRAM>
        <SOBCURR_STUDY_PATH_IND>N</SOBCURR_STUDY_PATH_IND>
        <SOBCURR_SURROGATE_ID>1830</SOBCURR_SURROGATE_ID>
        <SOBCURR_VERSION>0</SOBCURR_VERSION>
        <SOBCURR_USER_ID>GRAILS</SOBCURR_USER_ID>
        <SOBCURR_DATA_ORIGIN>GRAILS</SOBCURR_DATA_ORIGIN>
        <SOBCURR_VPDI_CODE/>
    </SOBCURR>
    <SORMCRL>
        <PROGRAM>BA</PROGRAM>
        <SORMCRL_CURR_RULE>22</SORMCRL_CURR_RULE>
        <SORMCRL_TERM_CODE_EFF>000000</SORMCRL_TERM_CODE_EFF>
        <SORMCRL_REC_IND>Y</SORMCRL_REC_IND>
        <SORMCRL_ADM_IND>Y</SORMCRL_ADM_IND>
        <SORMCRL_STU_IND>Y</SORMCRL_STU_IND>
        <SORMCRL_HIS_IND>N</SORMCRL_HIS_IND>
        <SORMCRL_DAU_IND>N</SORMCRL_DAU_IND>
        <SORMCRL_ACTIVITY_DATE>01-JAN-10</SORMCRL_ACTIVITY_DATE>
        <SORMCRL_SURROGATE_ID>1419</SORMCRL_SURROGATE_ID>
        <SORMCRL_VERSION>0</SORMCRL_VERSION>
        <SORMCRL_USER_ID>GRAILS</SORMCRL_USER_ID>
        <SORMCRL_DATA_ORIGIN>GRAILS</SORMCRL_DATA_ORIGIN>
        <SORMCRL_VPDI_CODE/>
    </SORMCRL>
    <SORCMJR>
        <PROGRAM>BA</PROGRAM>
        <SORCMJR_CURR_RULE>22</SORCMJR_CURR_RULE>
        <SORCMJR_CMJR_RULE>423</SORCMJR_CMJR_RULE>
        <SORCMJR_TERM_CODE_EFF>000000</SORCMJR_TERM_CODE_EFF>
        <SORCMJR_ADM_IND>Y</SORCMJR_ADM_IND>
        <SORCMJR_STU_IND>Y</SORCMJR_STU_IND>
        <SORCMJR_HIS_IND>Y</SORCMJR_HIS_IND>
        <SORCMJR_REC_IND>Y</SORCMJR_REC_IND>
        <SORCMJR_DAU_IND>Y</SORCMJR_DAU_IND>
        <SORCMJR_ACTIVITY_DATE>01-JAN-10</SORCMJR_ACTIVITY_DATE>
        <SORCMJR_MAJR_CODE>ART</SORCMJR_MAJR_CODE>
        <SORCMJR_DEPT_CODE/>
        <SORCMJR_DEGR_CDE/>
        <SORCMJR_EDI_QLFR/>
        <SORCMJR_EDI_VALUE/>
        <SORCMJR_DISP_WEB_IND>N</SORCMJR_DISP_WEB_IND>
        <SORCMJR_DESC/>
        <SORCMJR_AUTO_DEC_IND>N</SORCMJR_AUTO_DEC_IND>
        <SORCMJR_SURROGATE_ID>2872</SORCMJR_SURROGATE_ID>
        <SORCMJR_VERSION>0</SORCMJR_VERSION>
        <SORCMJR_USER_ID>GRAILS</SORCMJR_USER_ID>
        <SORCMJR_DATA_ORIGIN>GRAILS</SORCMJR_DATA_ORIGIN>
        <SORCMJR_VPDI_CODE/>
    </SORCMJR>
    <SORCMJR>
        <PROGRAM>BA</PROGRAM>
        <SORCMJR_CURR_RULE>22</SORCMJR_CURR_RULE>
        <SORCMJR_CMJR_RULE>424</SORCMJR_CMJR_RULE>
        <SORCMJR_TERM_CODE_EFF>000000</SORCMJR_TERM_CODE_EFF>
        <SORCMJR_ADM_IND>Y</SORCMJR_ADM_IND>
        <SORCMJR_STU_IND>Y</SORCMJR_STU_IND>
        <SORCMJR_HIS_IND>Y</SORCMJR_HIS_IND>
        <SORCMJR_REC_IND>Y</SORCMJR_REC_IND>
        <SORCMJR_DAU_IND>Y</SORCMJR_DAU_IND>
        <SORCMJR_ACTIVITY_DATE>01-JAN-10</SORCMJR_ACTIVITY_DATE>
        <SORCMJR_MAJR_CODE>ENGL</SORCMJR_MAJR_CODE>
        <SORCMJR_DEPT_CODE/>
        <SORCMJR_DEGR_CDE>2.0</SORCMJR_DEGR_CDE>
        <SORCMJR_EDI_QLFR>81</SORCMJR_EDI_QLFR>
        <SORCMJR_EDI_VALUE/>
        <SORCMJR_DISP_WEB_IND>N</SORCMJR_DISP_WEB_IND>
        <SORCMJR_DESC/>
        <SORCMJR_AUTO_DEC_IND>N</SORCMJR_AUTO_DEC_IND>
        <SORCMJR_SURROGATE_ID>2873</SORCMJR_SURROGATE_ID>
        <SORCMJR_VERSION>0</SORCMJR_VERSION>
        <SORCMJR_USER_ID>GRAILS</SORCMJR_USER_ID>
        <SORCMJR_DATA_ORIGIN>GRAILS</SORCMJR_DATA_ORIGIN>
        <SORCMJR_VPDI_CODE/>
    </SORCMJR>
    <SARWAPC>
        <PROGRAM>BA</PROGRAM>
        <MAJOR>ART</MAJOR>
        <SARWAPC_CURR_RULE>5</SARWAPC_CURR_RULE>
        <SARWAPC_CMJR_RULE>398</SARWAPC_CMJR_RULE>
        <SARWAPC_TERM_CODE_EFF>201410</SARWAPC_TERM_CODE_EFF>
        <SARWAPC_WAPP_CODE>TE</SARWAPC_WAPP_CODE>
    </SARWAPC>
    <SARWADF>
        <PROGRAM>BA</PROGRAM>
        <SARWADF_WAPP_CODE>CE</SARWADF_WAPP_CODE>
        <SARWADF_TERM_CODE_EFF>000000</SARWADF_TERM_CODE_EFF>
        <SARWADF_CURR_RULE>5</SARWADF_CURR_RULE>
        <SARWADF_CURR_RULE_2>6</SARWADF_CURR_RULE_2>
        <SARWADF_SSN_LN_IND>N</SARWADF_SSN_LN_IND>
        <SARWADF_AUTO_APPL_IND>N</SARWADF_AUTO_APPL_IND>
        <SARWADF_AUTO_PUSH_IND>N</SARWADF_AUTO_PUSH_IND>
        <SARWADF_AUTO_RECR_IND>N</SARWADF_AUTO_RECR_IND>
        <SARWADF_AUTO_DEC_IND>N</SARWADF_AUTO_DEC_IND>
        <SARWADF_AUTO_TRAN_IND>N</SARWADF_AUTO_TRAN_IND>
        <SARWADF_ACCEPT_WAIVER_IND>N</SARWADF_ACCEPT_WAIVER_IND>
        <SARWADF_TRAN_MISC_IND>N</SARWADF_TRAN_MISC_IND>
        <SARWADF_ONE_REC_APPL_IND>N</SARWADF_ONE_REC_APPL_IND>
    </SARWADF>

    <SMRRQCM>
        <BANNERID>HOS00001</BANNERID>
        <SMRRQCM_PIDM>37859</SMRRQCM_PIDM>
        <SMRRQCM_REQUEST_NO>1</SMRRQCM_REQUEST_NO>
        <SMRRQCM_TERM_CODE_EVAL>201410</SMRRQCM_TERM_CODE_EVAL>
        <SMRRQCM_PROCESS_IND>Y</SMRRQCM_PROCESS_IND>
        <SMRRQCM_DEGR_APPLY_IND>N</SMRRQCM_DEGR_APPLY_IND>
        <SMRRQCM_DEGR_UPDATE_IND>N</SMRRQCM_DEGR_UPDATE_IND>
        <SMRRQCM_USE_IP_CRSE_IND>N</SMRRQCM_USE_IP_CRSE_IND>
        <SMRRQCM_CRSE_ORDER_IND>T</SMRRQCM_CRSE_ORDER_IND>
        <SMRRQCM_UNUSED_AREA_IND>Y</SMRRQCM_UNUSED_AREA_IND>
        <SMRRQCM_UNUSED_CRSE_ATTR_IND>Y</SMRRQCM_UNUSED_CRSE_ATTR_IND>
        <SMRRQCM_REJECTION_IND>Y</SMRRQCM_REJECTION_IND>
        <SMRRQCM_CRSE_SEL_REPORT_IND>Y</SMRRQCM_CRSE_SEL_REPORT_IND>
        <SMRRQCM_REQUEST_DATE>01-JAN-2014</SMRRQCM_REQUEST_DATE>
        <SMRRQCM_GRDE_NUMERIC_VALUE>0</SMRRQCM_GRDE_NUMERIC_VALUE>
        <SMRRQCM_DETAIL_EXISTS_IND>N</SMRRQCM_DETAIL_EXISTS_IND>
        <SMRRQCM_PROGRAM>BA-ANTHRO</SMRRQCM_PROGRAM>
        <SMRRQCM_TERM_CODE_CTLG_1>201010</SMRRQCM_TERM_CODE_CTLG_1>
        <SMRRQCM_LEVL_CODE>UG</SMRRQCM_LEVL_CODE>
        <SMRRQCM_USER>GRAILS</SMRRQCM_USER>
        <SMRRQCM_ORIG_CURR_SOURCE>USER</SMRRQCM_ORIG_CURR_SOURCE>
        <SMRRQCM_CURR_SOURCE>USER</SMRRQCM_CURR_SOURCE>
        <SMRRQCM_CURR_SOURCE_CHG_IND>N</SMRRQCM_CURR_SOURCE_CHG_IND>
        <SMRRQCM_PROGRAM_CHG_IND>N</SMRRQCM_PROGRAM_CHG_IND>
        <SMRRQCM_TERM_1_CHG_IND>N</SMRRQCM_TERM_1_CHG_IND>
        <SMRRQCM_LEVL_CHG_IND>N</SMRRQCM_LEVL_CHG_IND>
        <SMRRQCM_CAMP_CHG_IND>N</SMRRQCM_CAMP_CHG_IND>
        <SMRRQCM_COLL_CHG_IND>N</SMRRQCM_COLL_CHG_IND>
        <SMRRQCM_DEGC_CHG_IND>N</SMRRQCM_DEGC_CHG_IND>
        <SMRRQCM_MAJR_1_CHG_IND>N</SMRRQCM_MAJR_1_CHG_IND>
        <SMRRQCM_DEPT_CHG_IND>N</SMRRQCM_DEPT_CHG_IND>
        <SMRRQCM_CONC_1_CHG_IND>N</SMRRQCM_CONC_1_CHG_IND>
        <SMRRQCM_CONC_1_2_CHG_IND>N</SMRRQCM_CONC_1_2_CHG_IND>
        <SMRRQCM_CONC_1_3_CHG_IND>N</SMRRQCM_CONC_1_3_CHG_IND>
        <SMRRQCM_MAJR_1_2_CHG_IND>N</SMRRQCM_MAJR_1_2_CHG_IND>
        <SMRRQCM_DEPT_1_2_CHG_IND>N</SMRRQCM_DEPT_1_2_CHG_IND>
        <SMRRQCM_CONC_121_CHG_IND>N</SMRRQCM_CONC_121_CHG_IND>
        <SMRRQCM_CONC_122_CHG_IND>N</SMRRQCM_CONC_122_CHG_IND>
        <SMRRQCM_CONC_123_CHG_IND>N</SMRRQCM_CONC_123_CHG_IND>
        <SMRRQCM_MINR_1_1_CHG_IND>N</SMRRQCM_MINR_1_1_CHG_IND>
        <SMRRQCM_MINR_1_2_CHG_IND>N</SMRRQCM_MINR_1_2_CHG_IND>
        <SMRRQCM_TERM_2_CHG_IND>N</SMRRQCM_TERM_2_CHG_IND>
        <SMRRQCM_MAJR_2_CHG_IND>N</SMRRQCM_MAJR_2_CHG_IND>
        <SMRRQCM_DEPT_2_CHG_IND>N</SMRRQCM_DEPT_2_CHG_IND>
        <SMRRQCM_CONC_2_CHG_IND>N</SMRRQCM_CONC_2_CHG_IND>
        <SMRRQCM_CONC_2_2_CHG_IND>N</SMRRQCM_CONC_2_2_CHG_IND>
        <SMRRQCM_CONC_2_3_CHG_IND>N</SMRRQCM_CONC_2_3_CHG_IND>
        <SMRRQCM_MAJR_2_2_CHG_IND>N</SMRRQCM_MAJR_2_2_CHG_IND>
        <SMRRQCM_DEPT_2_2_CHG_IND>N</SMRRQCM_DEPT_2_2_CHG_IND>
        <SMRRQCM_CONC_221_CHG_IND>N</SMRRQCM_CONC_221_CHG_IND>
        <SMRRQCM_CONC_222_CHG_IND>N</SMRRQCM_CONC_222_CHG_IND>
        <SMRRQCM_CONC_223_CHG_IND>N</SMRRQCM_CONC_223_CHG_IND>
        <SMRRQCM_MINR_2_1_CHG_IND>N</SMRRQCM_MINR_2_1_CHG_IND>
        <SMRRQCM_MINR_2_2_CHG_IND>N</SMRRQCM_MINR_2_2_CHG_IND>
        <SMRRQCM_PROG_CHG_IND>N</SMRRQCM_PROG_CHG_IND>
        <SMRRQCM_AREA_CHG_IND>N</SMRRQCM_AREA_CHG_IND>
        <SMRRQCM_GROUP_CHG_IND>N</SMRRQCM_GROUP_CHG_IND>
        <SMRRQCM_FEE_IND>N</SMRRQCM_FEE_IND>
    </SMRRQCM>

</APPLICANTDATA>
