<?xml version="1.0" encoding="Windows-1252" ?>

<!--***************************************************************************
Copyright 2017 Ellucian Company L.P. and its affiliates.
****************************************************************************-->

<PPREXAM_DATA>
    <PPREXAM>
        <PPREXAM_PIDM>49511</PPREXAM_PIDM>
        <PPREXAM_EXAM_CODE>03</PPREXAM_EXAM_CODE>
        <PPREXAM_EXAM_DATE>09081995</PPREXAM_EXAM_DATE>
        <PPREXAM_EXAM_SCORE>70</PPREXAM_EXAM_SCORE>
        <PPREXAM_ACTIVITY_DATE>06121995</PPREXAM_ACTIVITY_DATE>
        <PPREXAM_PASS_IND>P</PPREXAM_PASS_IND>
    </PPREXAM>
    <PPREXAM>
        <PPREXAM_PIDM>49512</PPREXAM_PIDM>
        <PPREXAM_EXAM_CODE>04</PPREXAM_EXAM_CODE>
        <PPREXAM_EXAM_DATE>09081995</PPREXAM_EXAM_DATE>
        <PPREXAM_EXAM_SCORE>85</PPREXAM_EXAM_SCORE>
        <PPREXAM_ACTIVITY_DATE>06121995</PPREXAM_ACTIVITY_DATE>
        <PPREXAM_PASS_IND>P</PPREXAM_PASS_IND>
    </PPREXAM>
    <PPREXAM>
        <PPREXAM_PIDM>49513</PPREXAM_PIDM>
        <PPREXAM_EXAM_CODE>05</PPREXAM_EXAM_CODE>
        <PPREXAM_EXAM_DATE>09081995</PPREXAM_EXAM_DATE>
        <PPREXAM_EXAM_SCORE>77</PPREXAM_EXAM_SCORE>
        <PPREXAM_ACTIVITY_DATE>06121995</PPREXAM_ACTIVITY_DATE>
        <PPREXAM_PASS_IND>P</PPREXAM_PASS_IND>
    </PPREXAM>
    <PPREXAM>
        <PPREXAM_PIDM>49514</PPREXAM_PIDM>
        <PPREXAM_EXAM_CODE>03</PPREXAM_EXAM_CODE>
        <PPREXAM_EXAM_DATE>09051995</PPREXAM_EXAM_DATE>
        <PPREXAM_EXAM_SCORE>75</PPREXAM_EXAM_SCORE>
        <PPREXAM_ACTIVITY_DATE>06121995</PPREXAM_ACTIVITY_DATE>
        <PPREXAM_PASS_IND>P</PPREXAM_PASS_IND>
    </PPREXAM>
</PPREXAM_DATA>