<?xml version="1.0" encoding="Windows-1252" ?>
<!-- *****************************************************************************
Copyright 2010-2016 Ellucian Company L.P. and its affiliates.
 ********************************************************************************* -->
<REGISTRATION>
    <!-- Add COdes to STVROVR -->
    <STVROVR>
        <STVROVR_CODE>ALL</STVROVR_CODE>
        <STVROVR_DESC>All Overrides</STVROVR_DESC>
        <STVROVR_ACTIVITY_DATE>01-OCT-2012</STVROVR_ACTIVITY_DATE>
        <STVROVR_SURROGATE_ID/>
        <STVROVR_VERSION/>
        <STVROVR_USER_ID>GRAILS_USER</STVROVR_USER_ID>
        <STVROVR_DATA_ORIGIN>GRAILS</STVROVR_DATA_ORIGIN>
        <STVROVR_VPDI_CODE/>
    </STVROVR>

    <STVROVR>
        <STVROVR_CODE>MAJOR</STVROVR_CODE>
        <STVROVR_DESC>Major</STVROVR_DESC>
        <STVROVR_ACTIVITY_DATE>01-OCT-2012</STVROVR_ACTIVITY_DATE>
        <STVROVR_SURROGATE_ID/>
        <STVROVR_VERSION/>
        <STVROVR_USER_ID>GRAILS_USER</STVROVR_USER_ID>
        <STVROVR_DATA_ORIGIN>GRAILS</STVROVR_DATA_ORIGIN>
        <STVROVR_VPDI_CODE/>
    </STVROVR>

    <STVROVR>
        <STVROVR_CODE>TIME</STVROVR_CODE>
        <STVROVR_DESC>Time</STVROVR_DESC>
        <STVROVR_ACTIVITY_DATE>01-OCT-2012</STVROVR_ACTIVITY_DATE>
        <STVROVR_SURROGATE_ID/>
        <STVROVR_VERSION/>
        <STVROVR_USER_ID>GRAILS_USER</STVROVR_USER_ID>
        <STVROVR_DATA_ORIGIN>GRAILS</STVROVR_DATA_ORIGIN>
        <STVROVR_VPDI_CODE/>
    </STVROVR>

    <STVROVR>
        <STVROVR_CODE>LEVEL</STVROVR_CODE>
        <STVROVR_DESC>Level</STVROVR_DESC>
        <STVROVR_ACTIVITY_DATE>01-OCT-2012</STVROVR_ACTIVITY_DATE>
        <STVROVR_SURROGATE_ID/>
        <STVROVR_VERSION/>
        <STVROVR_USER_ID>GRAILS_USER</STVROVR_USER_ID>
        <STVROVR_DATA_ORIGIN>GRAILS</STVROVR_DATA_ORIGIN>
        <STVROVR_VPDI_CODE/>
    </STVROVR>

    <!-- Add SFRRVOR data for 201410-->

    <SFRROVR>
        <SFRROVR_TERM_CODE>201410</SFRROVR_TERM_CODE>
        <SFRROVR_ROVR_CODE>MAJOR</SFRROVR_ROVR_CODE>
        <SFRROVR_DUPL_OVER>N</SFRROVR_DUPL_OVER>
        <SFRROVR_LINK_OVER>N</SFRROVR_LINK_OVER>
        <SFRROVR_CORQ_OVER>N</SFRROVR_CORQ_OVER>
        <SFRROVR_PREQ_OVER>N</SFRROVR_PREQ_OVER>
        <SFRROVR_TIME_OVER>N</SFRROVR_TIME_OVER>
        <SFRROVR_CAPC_OVER>N</SFRROVR_CAPC_OVER>
        <SFRROVR_LEVL_OVER>N</SFRROVR_LEVL_OVER>
        <SFRROVR_COLL_OVER>N</SFRROVR_COLL_OVER>
        <SFRROVR_MAJR_OVER>N</SFRROVR_MAJR_OVER>
        <SFRROVR_CLAS_OVER>N</SFRROVR_CLAS_OVER>
        <SFRROVR_APPR_OVER>N</SFRROVR_APPR_OVER>
        <SFRROVR_REPT_OVER>N</SFRROVR_REPT_OVER>
        <SFRROVR_RPTH_OVER>N</SFRROVR_RPTH_OVER>
        <SFRROVR_CAMP_OVER>N</SFRROVR_CAMP_OVER>
        <SFRROVR_ACTIVITY_DATE>31-OCT-11</SFRROVR_ACTIVITY_DATE>
        <SFRROVR_USER>GRAILS_USER</SFRROVR_USER>
        <SFRROVR_DEGC_OVER>N</SFRROVR_DEGC_OVER>
        <SFRROVR_PROG_OVER>N</SFRROVR_PROG_OVER>
        <SFRROVR_DEPT_OVER>N</SFRROVR_DEPT_OVER>
        <SFRROVR_ATTS_OVER>N</SFRROVR_ATTS_OVER>
        <SFRROVR_CHRT_OVER>N</SFRROVR_CHRT_OVER>
        <SFRROVR_MEXC_OVER>N</SFRROVR_MEXC_OVER>
        <SFRROVR_SURROGATE_ID/>
        <SFRROVR_VERSION/>
        <SFRROVR_USER_ID>grails_user</SFRROVR_USER_ID>
        <SFRROVR_DATA_ORIGIN>GRAILS</SFRROVR_DATA_ORIGIN>
        <SFRROVR_VPDI_CODE/>
    </SFRROVR>
    <SFRROVR>
        <SFRROVR_TERM_CODE>201410</SFRROVR_TERM_CODE>
        <SFRROVR_ROVR_CODE>ALL</SFRROVR_ROVR_CODE>
        <SFRROVR_DUPL_OVER>N</SFRROVR_DUPL_OVER>
        <SFRROVR_LINK_OVER>N</SFRROVR_LINK_OVER>
        <SFRROVR_CORQ_OVER>N</SFRROVR_CORQ_OVER>
        <SFRROVR_PREQ_OVER>N</SFRROVR_PREQ_OVER>
        <SFRROVR_TIME_OVER>N</SFRROVR_TIME_OVER>
        <SFRROVR_CAPC_OVER>N</SFRROVR_CAPC_OVER>
        <SFRROVR_LEVL_OVER>N</SFRROVR_LEVL_OVER>
        <SFRROVR_COLL_OVER>N</SFRROVR_COLL_OVER>
        <SFRROVR_MAJR_OVER>N</SFRROVR_MAJR_OVER>
        <SFRROVR_CLAS_OVER>N</SFRROVR_CLAS_OVER>
        <SFRROVR_APPR_OVER>N</SFRROVR_APPR_OVER>
        <SFRROVR_REPT_OVER>N</SFRROVR_REPT_OVER>
        <SFRROVR_RPTH_OVER>N</SFRROVR_RPTH_OVER>
        <SFRROVR_CAMP_OVER>N</SFRROVR_CAMP_OVER>
        <SFRROVR_ACTIVITY_DATE>31-OCT-11</SFRROVR_ACTIVITY_DATE>
        <SFRROVR_USER>GRAILS_USER</SFRROVR_USER>
        <SFRROVR_DEGC_OVER>N</SFRROVR_DEGC_OVER>
        <SFRROVR_PROG_OVER>N</SFRROVR_PROG_OVER>
        <SFRROVR_DEPT_OVER>N</SFRROVR_DEPT_OVER>
        <SFRROVR_ATTS_OVER>N</SFRROVR_ATTS_OVER>
        <SFRROVR_CHRT_OVER>N</SFRROVR_CHRT_OVER>
        <SFRROVR_MEXC_OVER>N</SFRROVR_MEXC_OVER>
        <SFRROVR_SURROGATE_ID/>
        <SFRROVR_VERSION/>
        <SFRROVR_USER_ID>grails_user</SFRROVR_USER_ID>
        <SFRROVR_DATA_ORIGIN>GRAILS</SFRROVR_DATA_ORIGIN>
        <SFRROVR_VPDI_CODE/>
    </SFRROVR>
    <SFRROVR>
        <SFRROVR_TERM_CODE>201410</SFRROVR_TERM_CODE>
        <SFRROVR_ROVR_CODE>TIME</SFRROVR_ROVR_CODE>
        <SFRROVR_DUPL_OVER>N</SFRROVR_DUPL_OVER>
        <SFRROVR_LINK_OVER>N</SFRROVR_LINK_OVER>
        <SFRROVR_CORQ_OVER>N</SFRROVR_CORQ_OVER>
        <SFRROVR_PREQ_OVER>N</SFRROVR_PREQ_OVER>
        <SFRROVR_TIME_OVER>N</SFRROVR_TIME_OVER>
        <SFRROVR_CAPC_OVER>N</SFRROVR_CAPC_OVER>
        <SFRROVR_LEVL_OVER>N</SFRROVR_LEVL_OVER>
        <SFRROVR_COLL_OVER>N</SFRROVR_COLL_OVER>
        <SFRROVR_MAJR_OVER>N</SFRROVR_MAJR_OVER>
        <SFRROVR_CLAS_OVER>N</SFRROVR_CLAS_OVER>
        <SFRROVR_APPR_OVER>N</SFRROVR_APPR_OVER>
        <SFRROVR_REPT_OVER>N</SFRROVR_REPT_OVER>
        <SFRROVR_RPTH_OVER>N</SFRROVR_RPTH_OVER>
        <SFRROVR_CAMP_OVER>N</SFRROVR_CAMP_OVER>
        <SFRROVR_ACTIVITY_DATE>31-OCT-11</SFRROVR_ACTIVITY_DATE>
        <SFRROVR_USER>GRAILS_USER</SFRROVR_USER>
        <SFRROVR_DEGC_OVER>N</SFRROVR_DEGC_OVER>
        <SFRROVR_PROG_OVER>N</SFRROVR_PROG_OVER>
        <SFRROVR_DEPT_OVER>N</SFRROVR_DEPT_OVER>
        <SFRROVR_ATTS_OVER>N</SFRROVR_ATTS_OVER>
        <SFRROVR_CHRT_OVER>N</SFRROVR_CHRT_OVER>
        <SFRROVR_MEXC_OVER>N</SFRROVR_MEXC_OVER>
        <SFRROVR_SURROGATE_ID/>
        <SFRROVR_VERSION/>
        <SFRROVR_USER_ID>grails_user</SFRROVR_USER_ID>
        <SFRROVR_DATA_ORIGIN>GRAILS</SFRROVR_DATA_ORIGIN>
        <SFRROVR_VPDI_CODE/>
    </SFRROVR>
    <SFRROVR>
        <SFRROVR_TERM_CODE>201410</SFRROVR_TERM_CODE>
        <SFRROVR_ROVR_CODE>LEVEL</SFRROVR_ROVR_CODE>
        <SFRROVR_DUPL_OVER>N</SFRROVR_DUPL_OVER>
        <SFRROVR_LINK_OVER>N</SFRROVR_LINK_OVER>
        <SFRROVR_CORQ_OVER>N</SFRROVR_CORQ_OVER>
        <SFRROVR_PREQ_OVER>N</SFRROVR_PREQ_OVER>
        <SFRROVR_TIME_OVER>N</SFRROVR_TIME_OVER>
        <SFRROVR_CAPC_OVER>N</SFRROVR_CAPC_OVER>
        <SFRROVR_LEVL_OVER>N</SFRROVR_LEVL_OVER>
        <SFRROVR_COLL_OVER>N</SFRROVR_COLL_OVER>
        <SFRROVR_MAJR_OVER>N</SFRROVR_MAJR_OVER>
        <SFRROVR_CLAS_OVER>N</SFRROVR_CLAS_OVER>
        <SFRROVR_APPR_OVER>N</SFRROVR_APPR_OVER>
        <SFRROVR_REPT_OVER>N</SFRROVR_REPT_OVER>
        <SFRROVR_RPTH_OVER>N</SFRROVR_RPTH_OVER>
        <SFRROVR_CAMP_OVER>N</SFRROVR_CAMP_OVER>
        <SFRROVR_ACTIVITY_DATE>31-OCT-11</SFRROVR_ACTIVITY_DATE>
        <SFRROVR_USER>GRAILS_USER</SFRROVR_USER>
        <SFRROVR_DEGC_OVER>N</SFRROVR_DEGC_OVER>
        <SFRROVR_PROG_OVER>N</SFRROVR_PROG_OVER>
        <SFRROVR_DEPT_OVER>N</SFRROVR_DEPT_OVER>
        <SFRROVR_ATTS_OVER>N</SFRROVR_ATTS_OVER>
        <SFRROVR_CHRT_OVER>N</SFRROVR_CHRT_OVER>
        <SFRROVR_MEXC_OVER>N</SFRROVR_MEXC_OVER>
        <SFRROVR_SURROGATE_ID/>
        <SFRROVR_VERSION/>
        <SFRROVR_USER_ID>grails_user</SFRROVR_USER_ID>
        <SFRROVR_DATA_ORIGIN>GRAILS</SFRROVR_DATA_ORIGIN>
        <SFRROVR_VPDI_CODE/>
    </SFRROVR>
    <!--  Seed data for Student Registration permit override-->
    <SFRSRPO>
        <BANNERID>HOS00001</BANNERID>
        <SFRSRPO_PIDM>37859</SFRSRPO_PIDM>
        <SFRSRPO_TERM_CODE>201410</SFRSRPO_TERM_CODE>
        <SFRSRPO_ROVR_CODE>ALL</SFRSRPO_ROVR_CODE>
        <SFRSRPO_SUBJ_CODE>ART</SFRSRPO_SUBJ_CODE>
        <SFRSRPO_CRSE_NUMB>100</SFRSRPO_CRSE_NUMB>
        <SFRSRPO_ACTIVITY_DATE>07-JUL-12</SFRSRPO_ACTIVITY_DATE>
        <SFRSRPO_SEQ_NUMB>01</SFRSRPO_SEQ_NUMB>
        <SFRSRPO_CRN>20001</SFRSRPO_CRN>
        <SFRSRPO_USER>GRAILS</SFRSRPO_USER>
        <SFRSRPO_SURROGATE_ID/>
        <SFRSRPO_VERSION/>
        <SFRSRPO_USER_ID/>
        <SFRSRPO_DATA_ORIGIN>GRAILS</SFRSRPO_DATA_ORIGIN>
        <SFRSRPO_VPDI_CODE/>
    </SFRSRPO>
    <SFRSRPO>
        <BANNERID>HOS00001</BANNERID>
        <SFRSRPO_PIDM>37859</SFRSRPO_PIDM>
        <SFRSRPO_TERM_CODE>201410</SFRSRPO_TERM_CODE>
        <SFRSRPO_ROVR_CODE>MAJOR</SFRSRPO_ROVR_CODE>
        <SFRSRPO_SUBJ_CODE>FNAR</SFRSRPO_SUBJ_CODE>
        <SFRSRPO_CRSE_NUMB>1040</SFRSRPO_CRSE_NUMB>
        <SFRSRPO_ACTIVITY_DATE>07-JUL-12</SFRSRPO_ACTIVITY_DATE>
        <SFRSRPO_SEQ_NUMB>02</SFRSRPO_SEQ_NUMB>
        <SFRSRPO_CRN>20005</SFRSRPO_CRN>
        <SFRSRPO_USER>GRAILS</SFRSRPO_USER>
        <SFRSRPO_SURROGATE_ID/>
        <SFRSRPO_VERSION/>
        <SFRSRPO_USER_ID/>
        <SFRSRPO_DATA_ORIGIN>GRAILS</SFRSRPO_DATA_ORIGIN>
        <SFRSRPO_VPDI_CODE/>
    </SFRSRPO>
    <SFRSRPO>
        <BANNERID>HOS00001</BANNERID>
        <SFRSRPO_PIDM>37859</SFRSRPO_PIDM>
        <SFRSRPO_TERM_CODE>201410</SFRSRPO_TERM_CODE>
        <SFRSRPO_ROVR_CODE>TIME</SFRSRPO_ROVR_CODE>
        <SFRSRPO_SUBJ_CODE>MUSC</SFRSRPO_SUBJ_CODE>
        <SFRSRPO_CRSE_NUMB>1000</SFRSRPO_CRSE_NUMB>
        <SFRSRPO_ACTIVITY_DATE>07-JUL-12</SFRSRPO_ACTIVITY_DATE>
        <SFRSRPO_SEQ_NUMB>01</SFRSRPO_SEQ_NUMB>
        <SFRSRPO_CRN>20007</SFRSRPO_CRN>
        <SFRSRPO_USER>GRAILS</SFRSRPO_USER>
        <SFRSRPO_SURROGATE_ID/>
        <SFRSRPO_VERSION/>
        <SFRSRPO_USER_ID/>
        <SFRSRPO_DATA_ORIGIN>GRAILS</SFRSRPO_DATA_ORIGIN>
        <SFRSRPO_VPDI_CODE/>
    </SFRSRPO>
    <SFRSRPO>
        <BANNERID>HOS00001</BANNERID>
        <SFRSRPO_PIDM>37859</SFRSRPO_PIDM>
        <SFRSRPO_TERM_CODE>201410</SFRSRPO_TERM_CODE>
        <SFRSRPO_ROVR_CODE>LEVEL</SFRSRPO_ROVR_CODE>
        <SFRSRPO_SUBJ_CODE>ENGL</SFRSRPO_SUBJ_CODE>
        <SFRSRPO_CRSE_NUMB>1005</SFRSRPO_CRSE_NUMB>
        <SFRSRPO_ACTIVITY_DATE>07-JUL-12</SFRSRPO_ACTIVITY_DATE>
        <SFRSRPO_SEQ_NUMB>01</SFRSRPO_SEQ_NUMB>
        <SFRSRPO_CRN>20013</SFRSRPO_CRN>
        <SFRSRPO_USER>GRAILS</SFRSRPO_USER>
        <SFRSRPO_SURROGATE_ID/>
        <SFRSRPO_VERSION/>
        <SFRSRPO_USER_ID/>
        <SFRSRPO_DATA_ORIGIN>GRAILS</SFRSRPO_DATA_ORIGIN>
        <SFRSRPO_VPDI_CODE/>
    </SFRSRPO>
    <!-- SFAMHRS PAGE seed-data-->
    <SFRMHRS>
        <SFRMHRS_TERM_CODE>201410</SFRMHRS_TERM_CODE>
        <SFRMHRS_LEVL_CODE>UG</SFRMHRS_LEVL_CODE>
        <SFRMHRS_MAX_HRS>1.5</SFRMHRS_MAX_HRS>
        <SFRMHRS_ACTIVITY_DATE>07-JAN-13</SFRMHRS_ACTIVITY_DATE>
        <SFRMHRS_MIN_HRS>1.0</SFRMHRS_MIN_HRS>
        <SFRMHRS_COLL_CODE>BU</SFRMHRS_COLL_CODE>
        <SFRMHRS_DEGC_CODE>BSA</SFRMHRS_DEGC_CODE>
        <SFRMHRS_ADMT_CODE>ST</SFRMHRS_ADMT_CODE>
        <SFRMHRS_CAMP_CODE>DEN</SFRMHRS_CAMP_CODE>
        <SFRMHRS_PROGRAM>PHD</SFRMHRS_PROGRAM>
        <SFRMHRS_LFST_CODE></SFRMHRS_LFST_CODE>
        <SFRMHRS_MAJR_CODE>CLV</SFRMHRS_MAJR_CODE>
        <SFRMHRS_DEPT_CODE>ENGR</SFRMHRS_DEPT_CODE>
        <SFRMHRS_PRIM_SEC_CDEP>P</SFRMHRS_PRIM_SEC_CDEP>
        <SFRMHRS_ATTS_CODE>FY</SFRMHRS_ATTS_CODE>
        <SFRMHRS_STYP_CODE>G</SFRMHRS_STYP_CODE>
        <SFRMHRS_CHRT_CODE>RISK</SFRMHRS_CHRT_CODE>
        <SFRMHRS_RESD_CODE>F</SFRMHRS_RESD_CODE>
        <SFRMHRS_ACTC_CODE>220</SFRMHRS_ACTC_CODE>
        <SFRMHRS_VTYP_CODE>J1</SFRMHRS_VTYP_CODE>
        <SFRMHRS_CLAS_CODE>SR</SFRMHRS_CLAS_CODE>
        <SFRMHRS_SEQ_NO>1</SFRMHRS_SEQ_NO>
        <SFRMHRS_USER_ID>GRAILS</SFRMHRS_USER_ID>
        <SFRMHRS_SURROGATE_ID/>
        <SFRMHRS_VERSION0/>
        <SFRMHRS_DATA_ORIGIN>GRAILS</SFRMHRS_DATA_ORIGIN>
        <SFRMHRS_VPDI_CODE/>
    </SFRMHRS>
</REGISTRATION>
