<?xml version="1.0"?>
<!-- *****************************************************************************
Copyright 2020-2020 Ellucian Company L.P. and its affiliates.
 ********************************************************************************* -->
<FINANCE_DATA>
    <FTVATYP>
        <FTVATYP_COAS_CODE>B</FTVATYP_COAS_CODE>
        <FTVATYP_ATYP_CODE>11</FTVATYP_ATYP_CODE>
        <FTVATYP_EFF_DATE>01-JUN-1950</FTVATYP_EFF_DATE>
        <FTVATYP_ACTIVITY_DATE>01-OCT-2020</FTVATYP_ACTIVITY_DATE>
        <FTVATYP_USER_ID>GRAILS</FTVATYP_USER_ID>
        <FTVATYP_NCHG_DATE>31-DEC-2099</FTVATYP_NCHG_DATE>
        <FTVATYP_TITLE>Cash and Cash Equivalent</FTVATYP_TITLE>
        <FTVATYP_STATUS_IND>A</FTVATYP_STATUS_IND>
        <FTVATYP_INTERNAL_ATYP_CODE>10</FTVATYP_INTERNAL_ATYP_CODE>
        <FTVATYP_ATYP_CODE_PRED>10</FTVATYP_ATYP_CODE_PRED>
        <FTVATYP_NORMAL_BAL>D</FTVATYP_NORMAL_BAL>
        <FTVATYP_VERSION>1</FTVATYP_VERSION>
        <FTVATYP_DATA_ORIGIN>GRAILS</FTVATYP_DATA_ORIGIN>
    </FTVATYP>
    <FTVATYP>
        <FTVATYP_COAS_CODE>B</FTVATYP_COAS_CODE>
        <FTVATYP_ATYP_CODE>51</FTVATYP_ATYP_CODE>
        <FTVATYP_EFF_DATE>01-JUN-1950</FTVATYP_EFF_DATE>
        <FTVATYP_ACTIVITY_DATE>01-OCT-2020</FTVATYP_ACTIVITY_DATE>
        <FTVATYP_USER_ID>GRAILS</FTVATYP_USER_ID>
        <FTVATYP_NCHG_DATE>01-DEC-2020</FTVATYP_NCHG_DATE>
        <FTVATYP_TITLE>Cash and Cash Equivalent</FTVATYP_TITLE>
        <FTVATYP_STATUS_IND>A</FTVATYP_STATUS_IND>
        <FTVATYP_INTERNAL_ATYP_CODE>10</FTVATYP_INTERNAL_ATYP_CODE>
        <FTVATYP_ATYP_CODE_PRED>51</FTVATYP_ATYP_CODE_PRED>
        <FTVATYP_NORMAL_BAL>D</FTVATYP_NORMAL_BAL>
        <FTVATYP_VERSION>1</FTVATYP_VERSION>
        <FTVATYP_DATA_ORIGIN>GRAILS</FTVATYP_DATA_ORIGIN>
    </FTVATYP>
    <FPRPODT>
        <FPRPODT_POHD_CODE>PR000002</FPRPODT_POHD_CODE>
        <FPRPODT_ACTIVITY_DATE>15-DEC-2006</FPRPODT_ACTIVITY_DATE>
        <FPRPODT_USER_ID>GRAILS</FPRPODT_USER_ID>
        <FPRPODT_ITEM>1</FPRPODT_ITEM>
        <FPRPODT_COMM_CODE>1122000000</FPRPODT_COMM_CODE>
        <FPRPODT_UOMS_CODE>EA</FPRPODT_UOMS_CODE>
        <FPRPODT_UNIT_PRICE>240</FPRPODT_UNIT_PRICE>
        <FPRPODT_QTY>1</FPRPODT_QTY>
        <FPRPODT_DISC_AMT>0</FPRPODT_DISC_AMT>
        <FPRPODT_TAX_AMT>0</FPRPODT_TAX_AMT>
        <FPRPODT_SUSP_IND>N</FPRPODT_SUSP_IND>
        <FPRPODT_TEXT_USAGE>S</FPRPODT_TEXT_USAGE>
        <FPRPODT_ADDL_CHRG_AMT>0</FPRPODT_ADDL_CHRG_AMT>
        <FPRPODT_TGRP_CODE>NT</FPRPODT_TGRP_CODE>
        <FPRPODT_DESC_CHGE_IND>N</FPRPODT_DESC_CHGE_IND>
        <FPRPODT_SHIP_CODE>EAST</FPRPODT_SHIP_CODE>
        <FPRPODT_REQD_DATE>20-DEC-2006</FPRPODT_REQD_DATE>
        <FPRPODT_DATA_ORIGIN>GRAILS</FPRPODT_DATA_ORIGIN>
    </FPRPODT>
    <FPRPODT>
        <FPRPODT_POHD_CODE>PR000002</FPRPODT_POHD_CODE>
        <FPRPODT_ACTIVITY_DATE>15-DEC-2006</FPRPODT_ACTIVITY_DATE>
        <FPRPODT_USER_ID>GRAILS</FPRPODT_USER_ID>
        <FPRPODT_ITEM>2</FPRPODT_ITEM>
        <FPRPODT_COMM_DESC>Tables</FPRPODT_COMM_DESC>
        <FPRPODT_UOMS_CODE>EA</FPRPODT_UOMS_CODE>
        <FPRPODT_UNIT_PRICE>780</FPRPODT_UNIT_PRICE>
        <FPRPODT_QTY>1</FPRPODT_QTY>
        <FPRPODT_DISC_AMT>0</FPRPODT_DISC_AMT>
        <FPRPODT_TAX_AMT>0</FPRPODT_TAX_AMT>
        <FPRPODT_SUSP_IND>N</FPRPODT_SUSP_IND>
        <FPRPODT_TEXT_USAGE>S</FPRPODT_TEXT_USAGE>
        <FPRPODT_ADDL_CHRG_AMT>0</FPRPODT_ADDL_CHRG_AMT>
        <FPRPODT_TGRP_CODE>NT</FPRPODT_TGRP_CODE>
        <FPRPODT_DESC_CHGE_IND>N</FPRPODT_DESC_CHGE_IND>
        <FPRPODT_SHIP_CODE>EAST</FPRPODT_SHIP_CODE>
        <FPRPODT_REQD_DATE>20-DEC-2006</FPRPODT_REQD_DATE>
        <FPRPODT_DATA_ORIGIN>GRAILS</FPRPODT_DATA_ORIGIN>
    </FPRPODT>
    <FPRPODT>
        <FPRPODT_POHD_CODE>P0000014</FPRPODT_POHD_CODE>
        <FPRPODT_ACTIVITY_DATE>15-DEC-2006</FPRPODT_ACTIVITY_DATE>
        <FPRPODT_USER_ID>GRAILS</FPRPODT_USER_ID>
        <FPRPODT_ITEM>1</FPRPODT_ITEM>
        <FPRPODT_COMM_CODE>1122000000</FPRPODT_COMM_CODE>
        <FPRPODT_UOMS_CODE>EA</FPRPODT_UOMS_CODE>
        <FPRPODT_UNIT_PRICE>240</FPRPODT_UNIT_PRICE>
        <FPRPODT_QTY>1</FPRPODT_QTY>
        <FPRPODT_DISC_AMT>0</FPRPODT_DISC_AMT>
        <FPRPODT_TAX_AMT>0</FPRPODT_TAX_AMT>
        <FPRPODT_SUSP_IND>N</FPRPODT_SUSP_IND>
        <FPRPODT_TEXT_USAGE>S</FPRPODT_TEXT_USAGE>
        <FPRPODT_ADDL_CHRG_AMT>0</FPRPODT_ADDL_CHRG_AMT>
        <FPRPODT_TGRP_CODE>NT</FPRPODT_TGRP_CODE>
        <FPRPODT_DESC_CHGE_IND>N</FPRPODT_DESC_CHGE_IND>
        <FPRPODT_SHIP_CODE>EAST</FPRPODT_SHIP_CODE>
        <FPRPODT_REQD_DATE>20-DEC-2006</FPRPODT_REQD_DATE>
        <FPRPODT_DATA_ORIGIN>GRAILS</FPRPODT_DATA_ORIGIN>
    </FPRPODT>
    <FPRPODT>
        <FPRPODT_POHD_CODE>P0000014</FPRPODT_POHD_CODE>
        <FPRPODT_ACTIVITY_DATE>15-DEC-2006</FPRPODT_ACTIVITY_DATE>
        <FPRPODT_USER_ID>GRAILS</FPRPODT_USER_ID>
        <FPRPODT_ITEM>2</FPRPODT_ITEM>
        <FPRPODT_COMM_DESC>Tables</FPRPODT_COMM_DESC>
        <FPRPODT_UOMS_CODE>EA</FPRPODT_UOMS_CODE>
        <FPRPODT_UNIT_PRICE>780</FPRPODT_UNIT_PRICE>
        <FPRPODT_QTY>1</FPRPODT_QTY>
        <FPRPODT_DISC_AMT>0</FPRPODT_DISC_AMT>
        <FPRPODT_TAX_AMT>0</FPRPODT_TAX_AMT>
        <FPRPODT_SUSP_IND>N</FPRPODT_SUSP_IND>
        <FPRPODT_TEXT_USAGE>S</FPRPODT_TEXT_USAGE>
        <FPRPODT_ADDL_CHRG_AMT>0</FPRPODT_ADDL_CHRG_AMT>
        <FPRPODT_TGRP_CODE>NT</FPRPODT_TGRP_CODE>
        <FPRPODT_DESC_CHGE_IND>N</FPRPODT_DESC_CHGE_IND>
        <FPRPODT_SHIP_CODE>EAST</FPRPODT_SHIP_CODE>
        <FPRPODT_REQD_DATE>20-DEC-2006</FPRPODT_REQD_DATE>
        <FPRPODT_DATA_ORIGIN>GRAILS</FPRPODT_DATA_ORIGIN>
    </FPRPODT>
    <FPRPODA>
        <FPRPODA_POHD_CODE>PR000002</FPRPODA_POHD_CODE>
        <FPRPODA_ITEM>1</FPRPODA_ITEM>
        <FPRPODA_SEQ_NUM>1</FPRPODA_SEQ_NUM>
        <FPRPODA_ACTIVITY_DATE>15-DEC-2006</FPRPODA_ACTIVITY_DATE>
        <FPRPODA_USER_ID>GRAILS</FPRPODA_USER_ID>
        <FPRPODA_AMT>240</FPRPODA_AMT>
        <FPRPODA_DISC_AMT>0</FPRPODA_DISC_AMT>
        <FPRPODA_TAX_AMT>0</FPRPODA_TAX_AMT>
        <FPRPODA_ADDL_CHRG_AMT>0</FPRPODA_ADDL_CHRG_AMT>
        <FPRPODA_FSYR_CODE>7</FPRPODA_FSYR_CODE>
        <FPRPODA_PERIOD>6</FPRPODA_PERIOD>
        <FPRPODA_RUCL_CODE_PO>PORD</FPRPODA_RUCL_CODE_PO>
        <FPRPODA_RUCL_CODE_LIQ>POLQ</FPRPODA_RUCL_CODE_LIQ>
        <FPRPODA_COAS_CODE>B</FPRPODA_COAS_CODE>
        <FPRPODA_FUND_CODE>1110D2</FPRPODA_FUND_CODE>
        <FPRPODA_ORGN_CODE>11004</FPRPODA_ORGN_CODE>
        <FPRPODA_ACCT_CODE>711052</FPRPODA_ACCT_CODE>
        <FPRPODA_PROG_CODE>10</FPRPODA_PROG_CODE>
        <FPRPODA_SUSP_IND>N</FPRPODA_SUSP_IND>
        <FPRPODA_NSF_SUSP_IND>N</FPRPODA_NSF_SUSP_IND>
        <FPRPODA_APPR_IND>N</FPRPODA_APPR_IND>
        <FPRPODA_NSF_OVERRIDE_IND>N</FPRPODA_NSF_OVERRIDE_IND>
        <FPRPODA_APPR_AMT_PCT>100</FPRPODA_APPR_AMT_PCT>
        <FPRPODA_DISC_AMT_PCT>0</FPRPODA_DISC_AMT_PCT>
        <FPRPODA_ADDL_AMT_PCT>0</FPRPODA_ADDL_AMT_PCT>
        <FPRPODA_TAX_AMT_PCT>0</FPRPODA_TAX_AMT_PCT>
    </FPRPODA>
    <FPRPODA>
        <FPRPODA_POHD_CODE>PR000002</FPRPODA_POHD_CODE>
        <FPRPODA_ITEM>2</FPRPODA_ITEM>
        <FPRPODA_SEQ_NUM>1</FPRPODA_SEQ_NUM>
        <FPRPODA_ACTIVITY_DATE>15-Dec-2006</FPRPODA_ACTIVITY_DATE>
        <FPRPODA_USER_ID>GRAILS</FPRPODA_USER_ID>
        <FPRPODA_AMT>522.6</FPRPODA_AMT>
        <FPRPODA_DISC_AMT>0</FPRPODA_DISC_AMT>
        <FPRPODA_TAX_AMT>0</FPRPODA_TAX_AMT>
        <FPRPODA_ADDL_CHRG_AMT>0</FPRPODA_ADDL_CHRG_AMT>
        <FPRPODA_FSYR_CODE>7</FPRPODA_FSYR_CODE>
        <FPRPODA_PERIOD>6</FPRPODA_PERIOD>
        <FPRPODA_RUCL_CODE_PO>PORD</FPRPODA_RUCL_CODE_PO>
        <FPRPODA_RUCL_CODE_LIQ>POLQ</FPRPODA_RUCL_CODE_LIQ>
        <FPRPODA_COAS_CODE>B</FPRPODA_COAS_CODE>
        <FPRPODA_FUND_CODE>1110D3</FPRPODA_FUND_CODE>
        <FPRPODA_ORGN_CODE>11004</FPRPODA_ORGN_CODE>
        <FPRPODA_ACCT_CODE>711052</FPRPODA_ACCT_CODE>
        <FPRPODA_PROG_CODE>10</FPRPODA_PROG_CODE>
        <FPRPODA_SUSP_IND>N</FPRPODA_SUSP_IND>
        <FPRPODA_NSF_SUSP_IND>N</FPRPODA_NSF_SUSP_IND>
        <FPRPODA_APPR_IND>N</FPRPODA_APPR_IND>
        <FPRPODA_NSF_OVERRIDE_IND>N</FPRPODA_NSF_OVERRIDE_IND>
        <FPRPODA_APPR_AMT_PCT>67</FPRPODA_APPR_AMT_PCT>
        <FPRPODA_DISC_AMT_PCT>67</FPRPODA_DISC_AMT_PCT>
        <FPRPODA_ADDL_AMT_PCT>67</FPRPODA_ADDL_AMT_PCT>
        <FPRPODA_TAX_AMT_PCT>67</FPRPODA_TAX_AMT_PCT>
    </FPRPODA>
    <FPRPODA>
        <FPRPODA_POHD_CODE>PR000002</FPRPODA_POHD_CODE>
        <FPRPODA_ITEM>2</FPRPODA_ITEM>
        <FPRPODA_SEQ_NUM>2</FPRPODA_SEQ_NUM>
        <FPRPODA_ACTIVITY_DATE>15-Dec-2006</FPRPODA_ACTIVITY_DATE>
        <FPRPODA_USER_ID>GRAILS</FPRPODA_USER_ID>
        <FPRPODA_AMT>257.4</FPRPODA_AMT>
        <FPRPODA_DISC_AMT>0</FPRPODA_DISC_AMT>
        <FPRPODA_TAX_AMT>0</FPRPODA_TAX_AMT>
        <FPRPODA_ADDL_CHRG_AMT>0</FPRPODA_ADDL_CHRG_AMT>
        <FPRPODA_FSYR_CODE>7</FPRPODA_FSYR_CODE>
        <FPRPODA_PERIOD>6</FPRPODA_PERIOD>
        <FPRPODA_RUCL_CODE_PO>PORD</FPRPODA_RUCL_CODE_PO>
        <FPRPODA_RUCL_CODE_LIQ>POLQ</FPRPODA_RUCL_CODE_LIQ>
        <FPRPODA_COAS_CODE>B</FPRPODA_COAS_CODE>
        <FPRPODA_FUND_CODE>1110D2</FPRPODA_FUND_CODE>
        <FPRPODA_ORGN_CODE>11004</FPRPODA_ORGN_CODE>
        <FPRPODA_ACCT_CODE>711052</FPRPODA_ACCT_CODE>
        <FPRPODA_PROG_CODE>10</FPRPODA_PROG_CODE>
        <FPRPODA_SUSP_IND>N</FPRPODA_SUSP_IND>
        <FPRPODA_NSF_SUSP_IND>N</FPRPODA_NSF_SUSP_IND>
        <FPRPODA_APPR_IND>N</FPRPODA_APPR_IND>
        <FPRPODA_NSF_OVERRIDE_IND>N</FPRPODA_NSF_OVERRIDE_IND>
        <FPRPODA_APPR_AMT_PCT>33</FPRPODA_APPR_AMT_PCT>
        <FPRPODA_DISC_AMT_PCT>33</FPRPODA_DISC_AMT_PCT>
        <FPRPODA_ADDL_AMT_PCT>33</FPRPODA_ADDL_AMT_PCT>
        <FPRPODA_TAX_AMT_PCT>33</FPRPODA_TAX_AMT_PCT>
    </FPRPODA>
    <FPRPODA>
        <FPRPODA_POHD_CODE>P0000014</FPRPODA_POHD_CODE>
        <FPRPODA_ITEM>1</FPRPODA_ITEM>
        <FPRPODA_SEQ_NUM>1</FPRPODA_SEQ_NUM>
        <FPRPODA_ACTIVITY_DATE>15-DEC-2006</FPRPODA_ACTIVITY_DATE>
        <FPRPODA_USER_ID>GRAILS</FPRPODA_USER_ID>
        <FPRPODA_AMT>240</FPRPODA_AMT>
        <FPRPODA_DISC_AMT>0</FPRPODA_DISC_AMT>
        <FPRPODA_TAX_AMT>0</FPRPODA_TAX_AMT>
        <FPRPODA_ADDL_CHRG_AMT>0</FPRPODA_ADDL_CHRG_AMT>
        <FPRPODA_FSYR_CODE>7</FPRPODA_FSYR_CODE>
        <FPRPODA_PERIOD>6</FPRPODA_PERIOD>
        <FPRPODA_RUCL_CODE_PO>PORD</FPRPODA_RUCL_CODE_PO>
        <FPRPODA_RUCL_CODE_LIQ>POLQ</FPRPODA_RUCL_CODE_LIQ>
        <FPRPODA_COAS_CODE>B</FPRPODA_COAS_CODE>
        <FPRPODA_FUND_CODE>1110D2</FPRPODA_FUND_CODE>
        <FPRPODA_ORGN_CODE>11004</FPRPODA_ORGN_CODE>
        <FPRPODA_ACCT_CODE>711052</FPRPODA_ACCT_CODE>
        <FPRPODA_PROG_CODE>10</FPRPODA_PROG_CODE>
        <FPRPODA_SUSP_IND>N</FPRPODA_SUSP_IND>
        <FPRPODA_NSF_SUSP_IND>N</FPRPODA_NSF_SUSP_IND>
        <FPRPODA_APPR_IND>N</FPRPODA_APPR_IND>
        <FPRPODA_NSF_OVERRIDE_IND>N</FPRPODA_NSF_OVERRIDE_IND>
        <FPRPODA_APPR_AMT_PCT>100</FPRPODA_APPR_AMT_PCT>
        <FPRPODA_DISC_AMT_PCT>0</FPRPODA_DISC_AMT_PCT>
        <FPRPODA_ADDL_AMT_PCT>0</FPRPODA_ADDL_AMT_PCT>
        <FPRPODA_TAX_AMT_PCT>0</FPRPODA_TAX_AMT_PCT>
    </FPRPODA>
    <FPRPODA>
        <FPRPODA_POHD_CODE>P0000014</FPRPODA_POHD_CODE>
        <FPRPODA_ITEM>2</FPRPODA_ITEM>
        <FPRPODA_SEQ_NUM>1</FPRPODA_SEQ_NUM>
        <FPRPODA_ACTIVITY_DATE>15-Dec-2006</FPRPODA_ACTIVITY_DATE>
        <FPRPODA_USER_ID>GRAILS</FPRPODA_USER_ID>
        <FPRPODA_AMT>522.6</FPRPODA_AMT>
        <FPRPODA_DISC_AMT>0</FPRPODA_DISC_AMT>
        <FPRPODA_TAX_AMT>0</FPRPODA_TAX_AMT>
        <FPRPODA_ADDL_CHRG_AMT>0</FPRPODA_ADDL_CHRG_AMT>
        <FPRPODA_FSYR_CODE>7</FPRPODA_FSYR_CODE>
        <FPRPODA_PERIOD>6</FPRPODA_PERIOD>
        <FPRPODA_RUCL_CODE_PO>PORD</FPRPODA_RUCL_CODE_PO>
        <FPRPODA_RUCL_CODE_LIQ>POLQ</FPRPODA_RUCL_CODE_LIQ>
        <FPRPODA_COAS_CODE>B</FPRPODA_COAS_CODE>
        <FPRPODA_FUND_CODE>1110D3</FPRPODA_FUND_CODE>
        <FPRPODA_ORGN_CODE>11004</FPRPODA_ORGN_CODE>
        <FPRPODA_ACCT_CODE>711052</FPRPODA_ACCT_CODE>
        <FPRPODA_PROG_CODE>10</FPRPODA_PROG_CODE>
        <FPRPODA_SUSP_IND>N</FPRPODA_SUSP_IND>
        <FPRPODA_NSF_SUSP_IND>N</FPRPODA_NSF_SUSP_IND>
        <FPRPODA_APPR_IND>N</FPRPODA_APPR_IND>
        <FPRPODA_NSF_OVERRIDE_IND>N</FPRPODA_NSF_OVERRIDE_IND>
        <FPRPODA_APPR_AMT_PCT>67</FPRPODA_APPR_AMT_PCT>
        <FPRPODA_DISC_AMT_PCT>67</FPRPODA_DISC_AMT_PCT>
        <FPRPODA_ADDL_AMT_PCT>67</FPRPODA_ADDL_AMT_PCT>
        <FPRPODA_TAX_AMT_PCT>67</FPRPODA_TAX_AMT_PCT>
    </FPRPODA>
    <FPRPODA>
        <FPRPODA_POHD_CODE>P0000014</FPRPODA_POHD_CODE>
        <FPRPODA_ITEM>2</FPRPODA_ITEM>
        <FPRPODA_SEQ_NUM>2</FPRPODA_SEQ_NUM>
        <FPRPODA_ACTIVITY_DATE>15-Dec-2006</FPRPODA_ACTIVITY_DATE>
        <FPRPODA_USER_ID>GRAILS</FPRPODA_USER_ID>
        <FPRPODA_AMT>257.4</FPRPODA_AMT>
        <FPRPODA_DISC_AMT>0</FPRPODA_DISC_AMT>
        <FPRPODA_TAX_AMT>0</FPRPODA_TAX_AMT>
        <FPRPODA_ADDL_CHRG_AMT>0</FPRPODA_ADDL_CHRG_AMT>
        <FPRPODA_FSYR_CODE>7</FPRPODA_FSYR_CODE>
        <FPRPODA_PERIOD>6</FPRPODA_PERIOD>
        <FPRPODA_RUCL_CODE_PO>PORD</FPRPODA_RUCL_CODE_PO>
        <FPRPODA_RUCL_CODE_LIQ>POLQ</FPRPODA_RUCL_CODE_LIQ>
        <FPRPODA_COAS_CODE>B</FPRPODA_COAS_CODE>
        <FPRPODA_FUND_CODE>1110D2</FPRPODA_FUND_CODE>
        <FPRPODA_ORGN_CODE>11004</FPRPODA_ORGN_CODE>
        <FPRPODA_ACCT_CODE>711052</FPRPODA_ACCT_CODE>
        <FPRPODA_PROG_CODE>10</FPRPODA_PROG_CODE>
        <FPRPODA_SUSP_IND>N</FPRPODA_SUSP_IND>
        <FPRPODA_NSF_SUSP_IND>N</FPRPODA_NSF_SUSP_IND>
        <FPRPODA_APPR_IND>N</FPRPODA_APPR_IND>
        <FPRPODA_NSF_OVERRIDE_IND>N</FPRPODA_NSF_OVERRIDE_IND>
        <FPRPODA_APPR_AMT_PCT>33</FPRPODA_APPR_AMT_PCT>
        <FPRPODA_DISC_AMT_PCT>33</FPRPODA_DISC_AMT_PCT>
        <FPRPODA_ADDL_AMT_PCT>33</FPRPODA_ADDL_AMT_PCT>
        <FPRPODA_TAX_AMT_PCT>33</FPRPODA_TAX_AMT_PCT>
    </FPRPODA>

    <FTVATYP>
        <FTVATYP_COAS_CODE>B</FTVATYP_COAS_CODE>
        <FTVATYP_ATYP_CODE>81</FTVATYP_ATYP_CODE>
        <FTVATYP_EFF_DATE>01-Jun-1950</FTVATYP_EFF_DATE>
        <FTVATYP_ACTIVITY_DATE>01-Jan-2020</FTVATYP_ACTIVITY_DATE>
        <FTVATYP_USER_ID>GRAILS</FTVATYP_USER_ID>
        <FTVATYP_NCHG_DATE>31-Dec-2099</FTVATYP_NCHG_DATE>
        <FTVATYP_TITLE>Cash and Cash Equivalent</FTVATYP_TITLE>
        <FTVATYP_STATUS_IND>A</FTVATYP_STATUS_IND>
        <FTVATYP_INTERNAL_ATYP_CODE>10</FTVATYP_INTERNAL_ATYP_CODE>
        <FTVATYP_ATYP_CODE_PRED>10</FTVATYP_ATYP_CODE_PRED>
        <FTVATYP_NORMAL_BAL>D</FTVATYP_NORMAL_BAL>
        <FTVATYP_DATA_ORIGIN>GRAILS</FTVATYP_DATA_ORIGIN>
    </FTVATYP>
</FINANCE_DATA>
