<?xml version="1.0" encoding="UTF-8"?>
<!-- *****************************************************************************
Copyright 2020 Ellucian Company L.P. and its affiliates.
 ********************************************************************************* -->
<ORDERITEM>
    <SKRGITM>
        <SKRGITM_TERM_CODE>202013</SKRGITM_TERM_CODE>
        <SKRGITM_CERT_CODE>BRTEST</SKRGITM_CERT_CODE>
        <SKRGITM_GITM_CODE>1S</SKRGITM_GITM_CODE>
        <SKRGITM_AVAILABLE_IND>Y</SKRGITM_AVAILABLE_IND>
        <SKRGITM_BASE_NUMBER>1</SKRGITM_BASE_NUMBER>
        <SKRGITM_MAX_NUMBER>1</SKRGITM_MAX_NUMBER>
        <SKRGITM_PRICE>0</SKRGITM_PRICE>
        <SKRGITM_ACTIVITY_DATE>01-JAN-10</SKRGITM_ACTIVITY_DATE>
        <SKRGITM_USER_ID>GRAILS</SKRGITM_USER_ID>
        <SKRGITM_SURROGATE_ID/>
        <SKRGITM_VERSION/>
        <SKRGITM_DATA_ORIGIN>GRAILS</SKRGITM_DATA_ORIGIN>
        <SKRGITM_VPDI_CODE/>
    </SKRGITM>
    <SKRGITM>
        <SKRGITM_TERM_CODE>202013</SKRGITM_TERM_CODE>
        <SKRGITM_CERT_CODE>BRTEST</SKRGITM_CERT_CODE>
        <SKRGITM_GITM_CODE>CG</SKRGITM_GITM_CODE>
        <SKRGITM_AVAILABLE_IND>Y</SKRGITM_AVAILABLE_IND>
        <SKRGITM_BASE_NUMBER>1</SKRGITM_BASE_NUMBER>
        <SKRGITM_MAX_NUMBER>1</SKRGITM_MAX_NUMBER>
        <SKRGITM_PRICE>40</SKRGITM_PRICE>
        <SKRGITM_ACTIVITY_DATE>01-JAN-10</SKRGITM_ACTIVITY_DATE>
        <SKRGITM_USER_ID>GRAILS</SKRGITM_USER_ID>
        <SKRGITM_SURROGATE_ID/>
        <SKRGITM_VERSION/>
        <SKRGITM_DATA_ORIGIN>GRAILS</SKRGITM_DATA_ORIGIN>
        <SKRGITM_VPDI_CODE/>
    </SKRGITM>
    <SKRGITM>
        <SKRGITM_TERM_CODE>202013</SKRGITM_TERM_CODE>
        <SKRGITM_CERT_CODE>BRTEST</SKRGITM_CERT_CODE>
        <SKRGITM_GITM_CODE>DVD</SKRGITM_GITM_CODE>
        <SKRGITM_AVAILABLE_IND>Y</SKRGITM_AVAILABLE_IND>
        <SKRGITM_BASE_NUMBER>1</SKRGITM_BASE_NUMBER>
        <SKRGITM_MAX_NUMBER>10</SKRGITM_MAX_NUMBER>
        <SKRGITM_PRICE>25</SKRGITM_PRICE>
        <SKRGITM_ACTIVITY_DATE>01-JAN-10</SKRGITM_ACTIVITY_DATE>
        <SKRGITM_USER_ID>GRAILS</SKRGITM_USER_ID>
        <SKRGITM_SURROGATE_ID/>
        <SKRGITM_VERSION/>
        <SKRGITM_DATA_ORIGIN>GRAILS</SKRGITM_DATA_ORIGIN>
        <SKRGITM_VPDI_CODE/>
    </SKRGITM>
    <SKRGITM>
        <SKRGITM_TERM_CODE>202013</SKRGITM_TERM_CODE>
        <SKRGITM_CERT_CODE>BRTEST</SKRGITM_CERT_CODE>
        <SKRGITM_GITM_CODE>GT2</SKRGITM_GITM_CODE>
        <SKRGITM_AVAILABLE_IND>Y</SKRGITM_AVAILABLE_IND>
        <SKRGITM_BASE_NUMBER>1</SKRGITM_BASE_NUMBER>
        <SKRGITM_MAX_NUMBER>3</SKRGITM_MAX_NUMBER>
        <SKRGITM_PRICE>15</SKRGITM_PRICE>
        <SKRGITM_ACTIVITY_DATE>01-JAN-10</SKRGITM_ACTIVITY_DATE>
        <SKRGITM_USER_ID>GRAILS</SKRGITM_USER_ID>
        <SKRGITM_SURROGATE_ID/>
        <SKRGITM_VERSION/>
        <SKRGITM_DATA_ORIGIN>GRAILS</SKRGITM_DATA_ORIGIN>
        <SKRGITM_VPDI_CODE/>
    </SKRGITM>
    <SKRGITM>
        <SKRGITM_TERM_CODE>202013</SKRGITM_TERM_CODE>
        <SKRGITM_CERT_CODE>BRTEST</SKRGITM_CERT_CODE>
        <SKRGITM_GITM_CODE>STU</SKRGITM_GITM_CODE>
        <SKRGITM_AVAILABLE_IND>Y</SKRGITM_AVAILABLE_IND>
        <SKRGITM_BASE_NUMBER>1</SKRGITM_BASE_NUMBER>
        <SKRGITM_MAX_NUMBER>1</SKRGITM_MAX_NUMBER>
        <SKRGITM_PRICE>0</SKRGITM_PRICE>
        <SKRGITM_ACTIVITY_DATE>01-JAN-10</SKRGITM_ACTIVITY_DATE>
        <SKRGITM_USER_ID>GRAILS</SKRGITM_USER_ID>
        <SKRGITM_SURROGATE_ID/>
        <SKRGITM_VERSION/>
        <SKRGITM_DATA_ORIGIN>GRAILS</SKRGITM_DATA_ORIGIN>
        <SKRGITM_VPDI_CODE/>
    </SKRGITM>
    <SKRGITM>
        <SKRGITM_TERM_CODE>202013</SKRGITM_TERM_CODE>
        <SKRGITM_CERT_CODE>GRTEST</SKRGITM_CERT_CODE>
        <SKRGITM_GITM_CODE>3S</SKRGITM_GITM_CODE>
        <SKRGITM_AVAILABLE_IND>Y</SKRGITM_AVAILABLE_IND>
        <SKRGITM_BASE_NUMBER>1</SKRGITM_BASE_NUMBER>
        <SKRGITM_MAX_NUMBER>1</SKRGITM_MAX_NUMBER>
        <SKRGITM_PRICE>100</SKRGITM_PRICE>
        <SKRGITM_ACTIVITY_DATE>01-JAN-10</SKRGITM_ACTIVITY_DATE>
        <SKRGITM_USER_ID>GRAILS</SKRGITM_USER_ID>
        <SKRGITM_SURROGATE_ID/>
        <SKRGITM_VERSION/>
        <SKRGITM_DATA_ORIGIN>GRAILS</SKRGITM_DATA_ORIGIN>
        <SKRGITM_VPDI_CODE/>
    </SKRGITM>
    <SKRGITM>
        <SKRGITM_TERM_CODE>202013</SKRGITM_TERM_CODE>
        <SKRGITM_CERT_CODE>GRTEST</SKRGITM_CERT_CODE>
        <SKRGITM_GITM_CODE>5</SKRGITM_GITM_CODE>
        <SKRGITM_AVAILABLE_IND>Y</SKRGITM_AVAILABLE_IND>
        <SKRGITM_BASE_NUMBER>1</SKRGITM_BASE_NUMBER>
        <SKRGITM_MAX_NUMBER>10</SKRGITM_MAX_NUMBER>
        <SKRGITM_PRICE>5</SKRGITM_PRICE>
        <SKRGITM_ACTIVITY_DATE>01-JAN-10</SKRGITM_ACTIVITY_DATE>
        <SKRGITM_USER_ID>GRAILS</SKRGITM_USER_ID>
        <SKRGITM_SURROGATE_ID/>
        <SKRGITM_VERSION/>
        <SKRGITM_DATA_ORIGIN>GRAILS</SKRGITM_DATA_ORIGIN>
        <SKRGITM_VPDI_CODE/>
    </SKRGITM>
    <SKRGITM>
        <SKRGITM_TERM_CODE>202013</SKRGITM_TERM_CODE>
        <SKRGITM_CERT_CODE>GRTEST</SKRGITM_CERT_CODE>
        <SKRGITM_GITM_CODE>GT2</SKRGITM_GITM_CODE>
        <SKRGITM_AVAILABLE_IND>Y</SKRGITM_AVAILABLE_IND>
        <SKRGITM_BASE_NUMBER>1</SKRGITM_BASE_NUMBER>
        <SKRGITM_MAX_NUMBER>3</SKRGITM_MAX_NUMBER>
        <SKRGITM_PRICE>15</SKRGITM_PRICE>
        <SKRGITM_ACTIVITY_DATE>01-JAN-10</SKRGITM_ACTIVITY_DATE>
        <SKRGITM_USER_ID>GRAILS</SKRGITM_USER_ID>
        <SKRGITM_SURROGATE_ID/>
        <SKRGITM_VERSION/>
        <SKRGITM_DATA_ORIGIN>GRAILS</SKRGITM_DATA_ORIGIN>
        <SKRGITM_VPDI_CODE/>
    </SKRGITM>
    <SKRGITM>
        <SKRGITM_TERM_CODE>202013</SKRGITM_TERM_CODE>
        <SKRGITM_CERT_CODE>GRTEST</SKRGITM_CERT_CODE>
        <SKRGITM_GITM_CODE>STU</SKRGITM_GITM_CODE>
        <SKRGITM_AVAILABLE_IND>Y</SKRGITM_AVAILABLE_IND>
        <SKRGITM_BASE_NUMBER>1</SKRGITM_BASE_NUMBER>
        <SKRGITM_MAX_NUMBER>1</SKRGITM_MAX_NUMBER>
        <SKRGITM_PRICE>100</SKRGITM_PRICE>
        <SKRGITM_ACTIVITY_DATE>01-JAN-10</SKRGITM_ACTIVITY_DATE>
        <SKRGITM_USER_ID>GRAILS</SKRGITM_USER_ID>
        <SKRGITM_SURROGATE_ID/>
        <SKRGITM_VERSION/>
        <SKRGITM_DATA_ORIGIN>GRAILS</SKRGITM_DATA_ORIGIN>
        <SKRGITM_VPDI_CODE/>
    </SKRGITM>
    <SKRGITM>
        <SKRGITM_TERM_CODE>202013</SKRGITM_TERM_CODE>
        <SKRGITM_CERT_CODE>GRTEST2</SKRGITM_CERT_CODE>
        <SKRGITM_GITM_CODE>1</SKRGITM_GITM_CODE>
        <SKRGITM_AVAILABLE_IND>Y</SKRGITM_AVAILABLE_IND>
        <SKRGITM_BASE_NUMBER>1</SKRGITM_BASE_NUMBER>
        <SKRGITM_MAX_NUMBER>12</SKRGITM_MAX_NUMBER>
        <SKRGITM_PRICE>12</SKRGITM_PRICE>
        <SKRGITM_ACTIVITY_DATE>01-JAN-10</SKRGITM_ACTIVITY_DATE>
        <SKRGITM_USER_ID>GRAILS</SKRGITM_USER_ID>
        <SKRGITM_SURROGATE_ID/>
        <SKRGITM_VERSION/>
        <SKRGITM_DATA_ORIGIN>GRAILS</SKRGITM_DATA_ORIGIN>
        <SKRGITM_VPDI_CODE/>
    </SKRGITM>
    <SKRGITM>
        <SKRGITM_TERM_CODE>202013</SKRGITM_TERM_CODE>
        <SKRGITM_CERT_CODE>GRTEST2</SKRGITM_CERT_CODE>
        <SKRGITM_GITM_CODE>CG</SKRGITM_GITM_CODE>
        <SKRGITM_AVAILABLE_IND>Y</SKRGITM_AVAILABLE_IND>
        <SKRGITM_BASE_NUMBER>1</SKRGITM_BASE_NUMBER>
        <SKRGITM_MAX_NUMBER>1</SKRGITM_MAX_NUMBER>
        <SKRGITM_PRICE>40</SKRGITM_PRICE>
        <SKRGITM_ACTIVITY_DATE>01-JAN-10</SKRGITM_ACTIVITY_DATE>
        <SKRGITM_USER_ID>GRAILS</SKRGITM_USER_ID>
        <SKRGITM_SURROGATE_ID/>
        <SKRGITM_VERSION/>
        <SKRGITM_DATA_ORIGIN>GRAILS</SKRGITM_DATA_ORIGIN>
        <SKRGITM_VPDI_CODE/>
    </SKRGITM>
    <SKRGITM>
        <SKRGITM_TERM_CODE>202013</SKRGITM_TERM_CODE>
        <SKRGITM_CERT_CODE>GRTEST2</SKRGITM_CERT_CODE>
        <SKRGITM_GITM_CODE>GT</SKRGITM_GITM_CODE>
        <SKRGITM_AVAILABLE_IND>Y</SKRGITM_AVAILABLE_IND>
        <SKRGITM_BASE_NUMBER>1</SKRGITM_BASE_NUMBER>
        <SKRGITM_MAX_NUMBER>10</SKRGITM_MAX_NUMBER>
        <SKRGITM_PRICE>10</SKRGITM_PRICE>
        <SKRGITM_ACTIVITY_DATE>01-JAN-10</SKRGITM_ACTIVITY_DATE>
        <SKRGITM_USER_ID>GRAILS</SKRGITM_USER_ID>
        <SKRGITM_SURROGATE_ID/>
        <SKRGITM_VERSION/>
        <SKRGITM_DATA_ORIGIN>GRAILS</SKRGITM_DATA_ORIGIN>
        <SKRGITM_VPDI_CODE/>
    </SKRGITM>
    <SKRGITM>
        <SKRGITM_TERM_CODE>202013</SKRGITM_TERM_CODE>
        <SKRGITM_CERT_CODE>GRTEST3</SKRGITM_CERT_CODE>
        <SKRGITM_GITM_CODE>CG</SKRGITM_GITM_CODE>
        <SKRGITM_AVAILABLE_IND>Y</SKRGITM_AVAILABLE_IND>
        <SKRGITM_BASE_NUMBER>1</SKRGITM_BASE_NUMBER>
        <SKRGITM_MAX_NUMBER>1</SKRGITM_MAX_NUMBER>
        <SKRGITM_PRICE>40</SKRGITM_PRICE>
        <SKRGITM_ACTIVITY_DATE>01-JAN-10</SKRGITM_ACTIVITY_DATE>
        <SKRGITM_USER_ID>GRAILS</SKRGITM_USER_ID>
        <SKRGITM_SURROGATE_ID/>
        <SKRGITM_VERSION/>
        <SKRGITM_DATA_ORIGIN>GRAILS</SKRGITM_DATA_ORIGIN>
        <SKRGITM_VPDI_CODE/>
    </SKRGITM>
    <SKRGITM>
        <SKRGITM_TERM_CODE>202013</SKRGITM_TERM_CODE>
        <SKRGITM_CERT_CODE>GRTEST3</SKRGITM_CERT_CODE>
        <SKRGITM_GITM_CODE>GT</SKRGITM_GITM_CODE>
        <SKRGITM_AVAILABLE_IND>Y</SKRGITM_AVAILABLE_IND>
        <SKRGITM_BASE_NUMBER>1</SKRGITM_BASE_NUMBER>
        <SKRGITM_MAX_NUMBER>10</SKRGITM_MAX_NUMBER>
        <SKRGITM_PRICE>10</SKRGITM_PRICE>
        <SKRGITM_ACTIVITY_DATE>01-JAN-10</SKRGITM_ACTIVITY_DATE>
        <SKRGITM_USER_ID>GRAILS</SKRGITM_USER_ID>
        <SKRGITM_SURROGATE_ID/>
        <SKRGITM_VERSION/>
        <SKRGITM_DATA_ORIGIN>GRAILS</SKRGITM_DATA_ORIGIN>
        <SKRGITM_VPDI_CODE/>
    </SKRGITM>
    <SKRGITM>
        <SKRGITM_TERM_CODE>202013</SKRGITM_TERM_CODE>
        <SKRGITM_CERT_CODE>BRTEST</SKRGITM_CERT_CODE>
        <SKRGITM_GITM_CODE>STU</SKRGITM_GITM_CODE>
        <SKRGITM_AVAILABLE_IND>Y</SKRGITM_AVAILABLE_IND>
        <SKRGITM_BASE_NUMBER>1</SKRGITM_BASE_NUMBER>
        <SKRGITM_MAX_NUMBER>1</SKRGITM_MAX_NUMBER>
        <SKRGITM_PRICE>0</SKRGITM_PRICE>
        <SKRGITM_ACTIVITY_DATE>01-JAN-10</SKRGITM_ACTIVITY_DATE>
        <SKRGITM_USER_ID>GRAILS</SKRGITM_USER_ID>
        <SKRGITM_SURROGATE_ID/>
        <SKRGITM_VERSION/>
        <SKRGITM_DATA_ORIGIN>GRAILS</SKRGITM_DATA_ORIGIN>
        <SKRGITM_VPDI_CODE/>
    </SKRGITM>
    <SKRGITM>
        <SKRGITM_TERM_CODE>202013</SKRGITM_TERM_CODE>
        <SKRGITM_CERT_CODE>APGRDSSEAT</SKRGITM_CERT_CODE>
        <SKRGITM_GITM_CODE>STU</SKRGITM_GITM_CODE>
        <SKRGITM_AVAILABLE_IND>Y</SKRGITM_AVAILABLE_IND>
        <SKRGITM_BASE_NUMBER>1</SKRGITM_BASE_NUMBER>
        <SKRGITM_MAX_NUMBER>1</SKRGITM_MAX_NUMBER>
        <SKRGITM_PRICE>100</SKRGITM_PRICE>
        <SKRGITM_ACTIVITY_DATE>01-JAN-10</SKRGITM_ACTIVITY_DATE>
        <SKRGITM_USER_ID>GRAILS</SKRGITM_USER_ID>
        <SKRGITM_SURROGATE_ID/>
        <SKRGITM_VERSION/>
        <SKRGITM_DATA_ORIGIN>GRAILS</SKRGITM_DATA_ORIGIN>
        <SKRGITM_VPDI_CODE/>
    </SKRGITM>
    <SKRGITM>
        <SKRGITM_TERM_CODE>202013</SKRGITM_TERM_CODE>
        <SKRGITM_CERT_CODE>APGRDSSEAT</SKRGITM_CERT_CODE>
        <SKRGITM_GITM_CODE>5</SKRGITM_GITM_CODE>
        <SKRGITM_AVAILABLE_IND>Y</SKRGITM_AVAILABLE_IND>
        <SKRGITM_BASE_NUMBER>1</SKRGITM_BASE_NUMBER>
        <SKRGITM_MAX_NUMBER>1</SKRGITM_MAX_NUMBER>
        <SKRGITM_PRICE>40</SKRGITM_PRICE>
        <SKRGITM_ACTIVITY_DATE>01-JAN-10</SKRGITM_ACTIVITY_DATE>
        <SKRGITM_USER_ID>GRAILS</SKRGITM_USER_ID>
        <SKRGITM_SURROGATE_ID/>
        <SKRGITM_VERSION/>
        <SKRGITM_DATA_ORIGIN>GRAILS</SKRGITM_DATA_ORIGIN>
        <SKRGITM_VPDI_CODE/>
    </SKRGITM>
    <SKRGITM>
        <SKRGITM_TERM_CODE>202013</SKRGITM_TERM_CODE>
        <SKRGITM_CERT_CODE>APGRDS</SKRGITM_CERT_CODE>
        <SKRGITM_GITM_CODE>5</SKRGITM_GITM_CODE>
        <SKRGITM_AVAILABLE_IND>Y</SKRGITM_AVAILABLE_IND>
        <SKRGITM_BASE_NUMBER>1</SKRGITM_BASE_NUMBER>
        <SKRGITM_MAX_NUMBER>1</SKRGITM_MAX_NUMBER>
        <SKRGITM_PRICE>40</SKRGITM_PRICE>
        <SKRGITM_ACTIVITY_DATE>01-JAN-10</SKRGITM_ACTIVITY_DATE>
        <SKRGITM_USER_ID>GRAILS</SKRGITM_USER_ID>
        <SKRGITM_SURROGATE_ID/>
        <SKRGITM_VERSION/>
        <SKRGITM_DATA_ORIGIN>GRAILS</SKRGITM_DATA_ORIGIN>
        <SKRGITM_VPDI_CODE/>
    </SKRGITM>
    <SKRGITM>
        <SKRGITM_TERM_CODE>202013</SKRGITM_TERM_CODE>
        <SKRGITM_CERT_CODE>APGRDSSEAT</SKRGITM_CERT_CODE>
        <SKRGITM_GITM_CODE>MISC</SKRGITM_GITM_CODE>
        <SKRGITM_AVAILABLE_IND>Y</SKRGITM_AVAILABLE_IND>
        <SKRGITM_BASE_NUMBER>1</SKRGITM_BASE_NUMBER>
        <SKRGITM_MAX_NUMBER>1</SKRGITM_MAX_NUMBER>
        <SKRGITM_PRICE>40</SKRGITM_PRICE>
        <SKRGITM_ACTIVITY_DATE>01-JAN-10</SKRGITM_ACTIVITY_DATE>
        <SKRGITM_USER_ID>GRAILS</SKRGITM_USER_ID>
        <SKRGITM_SURROGATE_ID/>
        <SKRGITM_VERSION/>
        <SKRGITM_DATA_ORIGIN>GRAILS</SKRGITM_DATA_ORIGIN>
        <SKRGITM_VPDI_CODE/>
    </SKRGITM>
    <SKRGORD>
        <BANNERID>A00050989</BANNERID>
        <SKRGORD_TERM_CODE>202013</SKRGORD_TERM_CODE>
        <SKRGORD_CERT_CODE>GRTEST</SKRGORD_CERT_CODE>
        <SKRGORD_SEQNO>1</SKRGORD_SEQNO>
        <SKRGORD_ACTIVE_IND>1</SKRGORD_ACTIVE_IND>
        <SKRGORD_PAID_IND>1</SKRGORD_PAID_IND>
        <SKRGORD_ACTIVITY_DATE>01-JAN-10</SKRGORD_ACTIVITY_DATE>
        <SKRGORD_USER_ID>GRAILS</SKRGORD_USER_ID>
        <SKRGORD_SURROGATE_ID/>
        <SKRGORD_VERSION/>
        <SKRGORD_ORDER_DATE>17-AUG-20</SKRGORD_ORDER_DATE>
        <SKRGORD_TRAN_NUMBER/>
        <SKRGORD_DATA_ORIGIN>GRAILS</SKRGORD_DATA_ORIGIN>
        <SKRGORD_VPDI_CODE/>
    </SKRGORD>
    <SKRGORD>
        <BANNERID>A00050000</BANNERID>
        <SKRGORD_TERM_CODE>202013</SKRGORD_TERM_CODE>
        <SKRGORD_CERT_CODE>APGRDSSEAT</SKRGORD_CERT_CODE>
        <SKRGORD_SEQNO>1</SKRGORD_SEQNO>
        <SKRGORD_ACTIVE_IND>1</SKRGORD_ACTIVE_IND>
        <SKRGORD_PAID_IND>1</SKRGORD_PAID_IND>
        <SKRGORD_ACTIVITY_DATE>01-JAN-10</SKRGORD_ACTIVITY_DATE>
        <SKRGORD_USER_ID>GRAILS</SKRGORD_USER_ID>
        <SKRGORD_SURROGATE_ID/>
        <SKRGORD_VERSION/>
        <SKRGORD_ORDER_DATE>17-AUG-20</SKRGORD_ORDER_DATE>
        <SKRGORD_TRAN_NUMBER/>
        <SKRGORD_DATA_ORIGIN>GRAILS</SKRGORD_DATA_ORIGIN>
        <SKRGORD_VPDI_CODE/>
    </SKRGORD>
    <SKRGORI>
        <BANNERID>A00050989</BANNERID>
        <SKRGORI_TERM_CODE>202013</SKRGORI_TERM_CODE>
        <SKRGORI_CERT_CODE>GRTEST</SKRGORI_CERT_CODE>
        <SKRGORI_GORD_SEQNO>1</SKRGORI_GORD_SEQNO>
        <SKRGORI_SEQNO>1</SKRGORI_SEQNO>
        <SKRGORI_GITM_CODE>STU</SKRGORI_GITM_CODE>
        <SKRGORI_QUANTITY>1</SKRGORI_QUANTITY>
        <SKRGORI_PRICE>100</SKRGORI_PRICE>
        <SKRGORI_ACTIVITY_DATE>01-JAN-10</SKRGORI_ACTIVITY_DATE>
        <SKRGORI_USER_ID>GRAILS</SKRGORI_USER_ID>
        <SKRGORI_SURROGATE_ID/>
        <SKRGORI_VERSION/>
        <SKRGORI_DATA_ORIGIN>GRAILS</SKRGORI_DATA_ORIGIN>
        <SKRGORI_VPDI_CODE/>
    </SKRGORI>
    <SKRGORI>
        <BANNERID>A00050000</BANNERID>
        <SKRGORI_TERM_CODE>202013</SKRGORI_TERM_CODE>
        <SKRGORI_CERT_CODE>APGRDSSEAT</SKRGORI_CERT_CODE>
        <SKRGORI_GORD_SEQNO>1</SKRGORI_GORD_SEQNO>
        <SKRGORI_SEQNO>1</SKRGORI_SEQNO>
        <SKRGORI_GITM_CODE>5</SKRGORI_GITM_CODE>
        <SKRGORI_QUANTITY>1</SKRGORI_QUANTITY>
        <SKRGORI_PRICE>100</SKRGORI_PRICE>
        <SKRGORI_ACTIVITY_DATE>01-JAN-10</SKRGORI_ACTIVITY_DATE>
        <SKRGORI_USER_ID>GRAILS</SKRGORI_USER_ID>
        <SKRGORI_SURROGATE_ID/>
        <SKRGORI_VERSION/>
        <SKRGORI_DATA_ORIGIN>GRAILS</SKRGORI_DATA_ORIGIN>
        <SKRGORI_VPDI_CODE/>
    </SKRGORI>
    <SKRGORI>
        <BANNERID>A00050000</BANNERID>
        <SKRGORI_TERM_CODE>202013</SKRGORI_TERM_CODE>
        <SKRGORI_CERT_CODE>APGRDSSEAT</SKRGORI_CERT_CODE>
        <SKRGORI_GORD_SEQNO>1</SKRGORI_GORD_SEQNO>
        <SKRGORI_SEQNO>2</SKRGORI_SEQNO>
        <SKRGORI_GITM_CODE>MISC</SKRGORI_GITM_CODE>
        <SKRGORI_QUANTITY>5</SKRGORI_QUANTITY>
        <SKRGORI_PRICE>100</SKRGORI_PRICE>
        <SKRGORI_ACTIVITY_DATE>01-JAN-10</SKRGORI_ACTIVITY_DATE>
        <SKRGORI_USER_ID>GRAILS</SKRGORI_USER_ID>
        <SKRGORI_SURROGATE_ID/>
        <SKRGORI_VERSION/>
        <SKRGORI_DATA_ORIGIN>GRAILS</SKRGORI_DATA_ORIGIN>
        <SKRGORI_VPDI_CODE/>
    </SKRGORI>
    <SKBGCAT>
        <BANNERID>A00017091</BANNERID>
        <SKBGCAT_TERM_CODE>202013</SKBGCAT_TERM_CODE>
        <SKBGCAT_CERT_CODE>GRTEST2</SKBGCAT_CERT_CODE>
        <SKBGCAT_ATTEND_IND>1</SKBGCAT_ATTEND_IND>
        <SKBGCAT_PAID_IND>1</SKBGCAT_PAID_IND>
        <SKBGCAT_ACTIVITY_DATE>01-JAN-10</SKBGCAT_ACTIVITY_DATE>
        <SKBGCAT_USER_ID>GRAILS</SKBGCAT_USER_ID>
        <SKBGCAT_SURROGATE_ID/>
        <SKBGCAT_VERSION/>
        <SKBGCAT_DGMR_SEQ_NO_1>1</SKBGCAT_DGMR_SEQ_NO_1>
        <SKBGCAT_DGMR_SEQ_NO_2/>
        <SKBGCAT_DATA_ORIGIN>GRAILS</SKBGCAT_DATA_ORIGIN>
        <SKBGCAT_VPDI_CODE/>
    </SKBGCAT>
    <SKRGITM>
        <SKRGITM_TERM_CODE>202013</SKRGITM_TERM_CODE>
        <SKRGITM_CERT_CODE>GRTEST2</SKRGITM_CERT_CODE>
        <SKRGITM_GITM_CODE>STU</SKRGITM_GITM_CODE>
        <SKRGITM_AVAILABLE_IND>Y</SKRGITM_AVAILABLE_IND>
        <SKRGITM_BASE_NUMBER>1</SKRGITM_BASE_NUMBER>
        <SKRGITM_MAX_NUMBER>1</SKRGITM_MAX_NUMBER>
        <SKRGITM_PRICE>0</SKRGITM_PRICE>
        <SKRGITM_ACTIVITY_DATE>01-JAN-10</SKRGITM_ACTIVITY_DATE>
        <SKRGITM_USER_ID>GRAILS</SKRGITM_USER_ID>
        <SKRGITM_SURROGATE_ID/>
        <SKRGITM_VERSION/>
        <SKRGITM_DATA_ORIGIN>GRAILS</SKRGITM_DATA_ORIGIN>
        <SKRGITM_VPDI_CODE/>
    </SKRGITM>
</ORDERITEM>
