<?xml version="1.0" encoding="Windows-1252" ?>
<!-- *****************************************************************************
Copyright 2020 Ellucian Company L.P. and its affiliates.
 ********************************************************************************* -->
<EPAF_DATA>
    <NOBTRAN>
        <NOBTRAN_TRANSACTION_NO>5727</NOBTRAN_TRANSACTION_NO>
        <BANNERID>HOPPA0001</BANNERID>
        <NOBTRAN_PIDM></NOBTRAN_PIDM>
        <NOBTRAN_EFFECTIVE_DATE>03/01/2020</NOBTRAN_EFFECTIVE_DATE>
        <NOBTRAN_ACAT_CODE>XTELE</NOBTRAN_ACAT_CODE>
        <NOBTRAN_TRANS_STATUS_IND>W</NOBTRAN_TRANS_STATUS_IND>
        <NOBTRAN_CREATED_DATE>03/01/2020</NOBTRAN_CREATED_DATE>
        <NOBTRAN_ORIGINATOR_USER_ID>PA00001</NOBTRAN_ORIGINATOR_USER_ID>
        <NOBTRAN_APPLY_IND>N</NOBTRAN_APPLY_IND>
    </NOBTRAN>
    <NOBTRAN>
        <NOBTRAN_TRANSACTION_NO>5728</NOBTRAN_TRANSACTION_NO>
        <BANNERID>HOPPA0002</BANNERID>
        <NOBTRAN_PIDM></NOBTRAN_PIDM>
        <NOBTRAN_EFFECTIVE_DATE>03/01/2020</NOBTRAN_EFFECTIVE_DATE>
        <NOBTRAN_ACAT_CODE>XTELE</NOBTRAN_ACAT_CODE>
        <NOBTRAN_TRANS_STATUS_IND>A</NOBTRAN_TRANS_STATUS_IND>
        <NOBTRAN_SUBMITTOR_USER_ID>PA00001</NOBTRAN_SUBMITTOR_USER_ID>
        <NOBTRAN_CREATED_DATE>03/01/2020</NOBTRAN_CREATED_DATE>
        <NOBTRAN_ORIGINATOR_USER_ID>PA00001</NOBTRAN_ORIGINATOR_USER_ID>
        <NOBTRAN_SUBMISSION_DATE>03/01/2020</NOBTRAN_SUBMISSION_DATE>
        <NOBTRAN_APPLY_IND>N</NOBTRAN_APPLY_IND>
    </NOBTRAN>
    <NOBTRAN>
        <NOBTRAN_TRANSACTION_NO>5729</NOBTRAN_TRANSACTION_NO>
        <BANNERID>HOPPA0003</BANNERID>
        <NOBTRAN_PIDM></NOBTRAN_PIDM>
        <NOBTRAN_EFFECTIVE_DATE>03/01/2020</NOBTRAN_EFFECTIVE_DATE>
        <NOBTRAN_ACAT_CODE>XADTEL</NOBTRAN_ACAT_CODE>
        <NOBTRAN_TRANS_STATUS_IND>P</NOBTRAN_TRANS_STATUS_IND>
        <NOBTRAN_SUBMITTOR_USER_ID>PA00001</NOBTRAN_SUBMITTOR_USER_ID>
        <NOBTRAN_CREATED_DATE>03/01/2020</NOBTRAN_CREATED_DATE>
        <NOBTRAN_ORIGINATOR_USER_ID>PA00001</NOBTRAN_ORIGINATOR_USER_ID>
        <NOBTRAN_SUBMISSION_DATE>03/01/2020</NOBTRAN_SUBMISSION_DATE>
        <NOBTRAN_APPLY_IND>N</NOBTRAN_APPLY_IND>
    </NOBTRAN>

    <NORTRAN>
        <NORTRAN_TRANSACTION_NO>5727</NORTRAN_TRANSACTION_NO>
        <BANNERID>HOPPA0001</BANNERID>
        <NOBTRAN_ACAT_CODE>XTELE</NOBTRAN_ACAT_CODE>
        <NORTRAN_APTY_CODE>XTELE</NORTRAN_APTY_CODE>
        <NORTRAN_AUFM_CODE>PPAIDEN</NORTRAN_AUFM_CODE>
        <NORTRAN_AUBK_CODE>SPRTELE</NORTRAN_AUBK_CODE>
        <NORTRAN_AUFD_CODE>SPRTELE_ADDR_SEQNO</NORTRAN_AUFD_CODE>
        <NORTRAN_APPLY_STATUS_IND>P</NORTRAN_APPLY_STATUS_IND>
        <NORTRAN_DISPLAY_SEQ_NO>2.5</NORTRAN_DISPLAY_SEQ_NO>
    </NORTRAN>
    <NORTRAN>
        <NORTRAN_TRANSACTION_NO>5727</NORTRAN_TRANSACTION_NO>
        <BANNERID>HOPPA0001</BANNERID>
        <NOBTRAN_ACAT_CODE>XTELE</NOBTRAN_ACAT_CODE>
        <NORTRAN_APTY_CODE>XTELE</NORTRAN_APTY_CODE>
        <NORTRAN_AUFM_CODE>PPAIDEN</NORTRAN_AUFM_CODE>
        <NORTRAN_AUBK_CODE>SPRTELE</NORTRAN_AUBK_CODE>
        <NORTRAN_AUFD_CODE>SPRTELE_ATYP_CODE</NORTRAN_AUFD_CODE>
        <NORTRAN_APPLY_STATUS_IND>P</NORTRAN_APPLY_STATUS_IND>
        <NORTRAN_DISPLAY_SEQ_NO>2</NORTRAN_DISPLAY_SEQ_NO>
    </NORTRAN>
    <NORTRAN>
        <NORTRAN_TRANSACTION_NO>5727</NORTRAN_TRANSACTION_NO>
        <BANNERID>HOPPA0001</BANNERID>
        <NOBTRAN_ACAT_CODE>XTELE</NOBTRAN_ACAT_CODE>
        <NORTRAN_APTY_CODE>XTELE</NORTRAN_APTY_CODE>
        <NORTRAN_AUFM_CODE>PPAIDEN</NORTRAN_AUFM_CODE>
        <NORTRAN_AUBK_CODE>SPRTELE</NORTRAN_AUBK_CODE>
        <NORTRAN_AUFD_CODE>SPRTELE_COMMENT</NORTRAN_AUFD_CODE>
        <NORTRAN_APPLY_STATUS_IND>P</NORTRAN_APPLY_STATUS_IND>
        <NORTRAN_DISPLAY_SEQ_NO>10</NORTRAN_DISPLAY_SEQ_NO>
    </NORTRAN>
    <NORTRAN>
        <NORTRAN_TRANSACTION_NO>5727</NORTRAN_TRANSACTION_NO>
        <BANNERID>HOPPA0001</BANNERID>
        <NOBTRAN_ACAT_CODE>XTELE</NOBTRAN_ACAT_CODE>
        <NORTRAN_APTY_CODE>XTELE</NORTRAN_APTY_CODE>
        <NORTRAN_AUFM_CODE>PPAIDEN</NORTRAN_AUFM_CODE>
        <NORTRAN_AUBK_CODE>SPRTELE</NORTRAN_AUBK_CODE>
        <NORTRAN_AUFD_CODE>SPRTELE_CTRY_CODE_PHONE</NORTRAN_AUFD_CODE>
        <NORTRAN_APPLY_STATUS_IND>P</NORTRAN_APPLY_STATUS_IND>
        <NORTRAN_DISPLAY_SEQ_NO>5.5</NORTRAN_DISPLAY_SEQ_NO>
    </NORTRAN>
    <NORTRAN>
        <NORTRAN_TRANSACTION_NO>5727</NORTRAN_TRANSACTION_NO>
        <BANNERID>HOPPA0001</BANNERID>
        <NOBTRAN_ACAT_CODE>XTELE</NOBTRAN_ACAT_CODE>
        <NORTRAN_APTY_CODE>XTELE</NORTRAN_APTY_CODE>
        <NORTRAN_AUFM_CODE>PPAIDEN</NORTRAN_AUFM_CODE>
        <NORTRAN_AUBK_CODE>SPRTELE</NORTRAN_AUBK_CODE>
        <NORTRAN_AUFD_CODE>SPRTELE_INTL_ACCESS</NORTRAN_AUFD_CODE>
        <NORTRAN_APPLY_STATUS_IND>P</NORTRAN_APPLY_STATUS_IND>
        <NORTRAN_DISPLAY_SEQ_NO>6</NORTRAN_DISPLAY_SEQ_NO>
    </NORTRAN>
    <NORTRAN>
        <NORTRAN_TRANSACTION_NO>5727</NORTRAN_TRANSACTION_NO>
        <BANNERID>HOPPA0001</BANNERID>
        <NOBTRAN_ACAT_CODE>XTELE</NOBTRAN_ACAT_CODE>
        <NORTRAN_APTY_CODE>XTELE</NORTRAN_APTY_CODE>
        <NORTRAN_AUFM_CODE>PPAIDEN</NORTRAN_AUFM_CODE>
        <NORTRAN_AUBK_CODE>SPRTELE</NORTRAN_AUBK_CODE>
        <NORTRAN_AUFD_CODE>SPRTELE_PHONE_AREA</NORTRAN_AUFD_CODE>
        <NORTRAN_VALUE>516</NORTRAN_VALUE>
        <NORTRAN_APPLY_STATUS_IND>P</NORTRAN_APPLY_STATUS_IND>
        <NORTRAN_DISPLAY_SEQ_NO>3</NORTRAN_DISPLAY_SEQ_NO>
    </NORTRAN>
    <NORTRAN>
        <NORTRAN_TRANSACTION_NO>5727</NORTRAN_TRANSACTION_NO>
        <BANNERID>HOPPA0001</BANNERID>
        <NOBTRAN_ACAT_CODE>XTELE</NOBTRAN_ACAT_CODE>
        <NORTRAN_APTY_CODE>XTELE</NORTRAN_APTY_CODE>
        <NORTRAN_AUFM_CODE>PPAIDEN</NORTRAN_AUFM_CODE>
        <NORTRAN_AUBK_CODE>SPRTELE</NORTRAN_AUBK_CODE>
        <NORTRAN_AUFD_CODE>SPRTELE_PHONE_EXT</NORTRAN_AUFD_CODE>
        <NORTRAN_APPLY_STATUS_IND>P</NORTRAN_APPLY_STATUS_IND>
        <NORTRAN_DISPLAY_SEQ_NO>5</NORTRAN_DISPLAY_SEQ_NO>
    </NORTRAN>
    <NORTRAN>
        <NORTRAN_TRANSACTION_NO>5727</NORTRAN_TRANSACTION_NO>
        <BANNERID>HOPPA0001</BANNERID>
        <NOBTRAN_ACAT_CODE>XTELE</NOBTRAN_ACAT_CODE>
        <NORTRAN_APTY_CODE>XTELE</NORTRAN_APTY_CODE>
        <NORTRAN_AUFM_CODE>PPAIDEN</NORTRAN_AUFM_CODE>
        <NORTRAN_AUBK_CODE>SPRTELE</NORTRAN_AUBK_CODE>
        <NORTRAN_AUFD_CODE>SPRTELE_PHONE_NUMBER</NORTRAN_AUFD_CODE>
        <NORTRAN_VALUE>741-1924</NORTRAN_VALUE>
        <NORTRAN_APPLY_STATUS_IND>P</NORTRAN_APPLY_STATUS_IND>
        <NORTRAN_DISPLAY_SEQ_NO>4</NORTRAN_DISPLAY_SEQ_NO>
    </NORTRAN>
    <NORTRAN>
        <NORTRAN_TRANSACTION_NO>5727</NORTRAN_TRANSACTION_NO>
        <BANNERID>HOPPA0001</BANNERID>
        <NOBTRAN_ACAT_CODE>XTELE</NOBTRAN_ACAT_CODE>
        <NORTRAN_APTY_CODE>XTELE</NORTRAN_APTY_CODE>
        <NORTRAN_AUFM_CODE>PPAIDEN</NORTRAN_AUFM_CODE>
        <NORTRAN_AUBK_CODE>SPRTELE</NORTRAN_AUBK_CODE>
        <NORTRAN_AUFD_CODE>SPRTELE_PRIMARY_IND</NORTRAN_AUFD_CODE>
        <NORTRAN_VALUE>Y</NORTRAN_VALUE>
        <NORTRAN_APPLY_STATUS_IND>P</NORTRAN_APPLY_STATUS_IND>
        <NORTRAN_DISPLAY_SEQ_NO>7</NORTRAN_DISPLAY_SEQ_NO>
    </NORTRAN>
    <NORTRAN>
        <NORTRAN_TRANSACTION_NO>5727</NORTRAN_TRANSACTION_NO>
        <BANNERID>HOPPA0001</BANNERID>
        <NOBTRAN_ACAT_CODE>XTELE</NOBTRAN_ACAT_CODE>
        <NORTRAN_APTY_CODE>XTELE</NORTRAN_APTY_CODE>
        <NORTRAN_AUFM_CODE>PPAIDEN</NORTRAN_AUFM_CODE>
        <NORTRAN_AUBK_CODE>SPRTELE</NORTRAN_AUBK_CODE>
        <NORTRAN_AUFD_CODE>SPRTELE_SEQNO</NORTRAN_AUFD_CODE>
        <NORTRAN_APPLY_STATUS_IND>P</NORTRAN_APPLY_STATUS_IND>
        <NORTRAN_DISPLAY_SEQ_NO>1.5</NORTRAN_DISPLAY_SEQ_NO>
    </NORTRAN>
    <NORTRAN>
        <NORTRAN_TRANSACTION_NO>5727</NORTRAN_TRANSACTION_NO>
        <BANNERID>HOPPA0001</BANNERID>
        <NOBTRAN_ACAT_CODE>XTELE</NOBTRAN_ACAT_CODE>
        <NORTRAN_APTY_CODE>XTELE</NORTRAN_APTY_CODE>
        <NORTRAN_AUFM_CODE>PPAIDEN</NORTRAN_AUFM_CODE>
        <NORTRAN_AUBK_CODE>SPRTELE</NORTRAN_AUBK_CODE>
        <NORTRAN_AUFD_CODE>SPRTELE_STATUS_IND</NORTRAN_AUFD_CODE>
        <NORTRAN_APPLY_STATUS_IND>P</NORTRAN_APPLY_STATUS_IND>
        <NORTRAN_DISPLAY_SEQ_NO>9</NORTRAN_DISPLAY_SEQ_NO>
    </NORTRAN>
    <NORTRAN>
        <NORTRAN_TRANSACTION_NO>5727</NORTRAN_TRANSACTION_NO>
        <BANNERID>HOPPA0001</BANNERID>
        <NOBTRAN_ACAT_CODE>XTELE</NOBTRAN_ACAT_CODE>
        <NORTRAN_APTY_CODE>XTELE</NORTRAN_APTY_CODE>
        <NORTRAN_AUFM_CODE>PPAIDEN</NORTRAN_AUFM_CODE>
        <NORTRAN_AUBK_CODE>SPRTELE</NORTRAN_AUBK_CODE>
        <NORTRAN_AUFD_CODE>SPRTELE_TELE_CODE</NORTRAN_AUFD_CODE>
        <NORTRAN_VALUE>CELL</NORTRAN_VALUE>
        <NORTRAN_APPLY_STATUS_IND>P</NORTRAN_APPLY_STATUS_IND>
        <NORTRAN_DISPLAY_SEQ_NO>1</NORTRAN_DISPLAY_SEQ_NO>
    </NORTRAN>
    <NORTRAN>
        <NORTRAN_TRANSACTION_NO>5727</NORTRAN_TRANSACTION_NO>
        <BANNERID>HOPPA0001</BANNERID>
        <NOBTRAN_ACAT_CODE>XTELE</NOBTRAN_ACAT_CODE>
        <NORTRAN_APTY_CODE>XTELE</NORTRAN_APTY_CODE>
        <NORTRAN_AUFM_CODE>PPAIDEN</NORTRAN_AUFM_CODE>
        <NORTRAN_AUBK_CODE>SPRTELE</NORTRAN_AUBK_CODE>
        <NORTRAN_AUFD_CODE>SPRTELE_UNLIST_IND</NORTRAN_AUFD_CODE>
        <NORTRAN_APPLY_STATUS_IND>P</NORTRAN_APPLY_STATUS_IND>
        <NORTRAN_DISPLAY_SEQ_NO>8</NORTRAN_DISPLAY_SEQ_NO>
    </NORTRAN>
    <NORTRAN>
        <NORTRAN_TRANSACTION_NO>5728</NORTRAN_TRANSACTION_NO>
        <BANNERID>HOPPA0002</BANNERID>
        <NOBTRAN_ACAT_CODE>XTELE</NOBTRAN_ACAT_CODE>
        <NORTRAN_APTY_CODE>XTELE</NORTRAN_APTY_CODE>
        <NORTRAN_AUFM_CODE>PPAIDEN</NORTRAN_AUFM_CODE>
        <NORTRAN_AUBK_CODE>SPRTELE</NORTRAN_AUBK_CODE>
        <NORTRAN_AUFD_CODE>SPRTELE_ADDR_SEQNO</NORTRAN_AUFD_CODE>
        <NORTRAN_APPLY_STATUS_IND>P</NORTRAN_APPLY_STATUS_IND>
        <NORTRAN_DISPLAY_SEQ_NO>2.5</NORTRAN_DISPLAY_SEQ_NO>
    </NORTRAN>
    <NORTRAN>
        <NORTRAN_TRANSACTION_NO>5728</NORTRAN_TRANSACTION_NO>
        <BANNERID>HOPPA0002</BANNERID>
        <NOBTRAN_ACAT_CODE>XTELE</NOBTRAN_ACAT_CODE>
        <NORTRAN_APTY_CODE>XTELE</NORTRAN_APTY_CODE>
        <NORTRAN_AUFM_CODE>PPAIDEN</NORTRAN_AUFM_CODE>
        <NORTRAN_AUBK_CODE>SPRTELE</NORTRAN_AUBK_CODE>
        <NORTRAN_AUFD_CODE>SPRTELE_ATYP_CODE</NORTRAN_AUFD_CODE>
        <NORTRAN_APPLY_STATUS_IND>P</NORTRAN_APPLY_STATUS_IND>
        <NORTRAN_DISPLAY_SEQ_NO>2</NORTRAN_DISPLAY_SEQ_NO>
    </NORTRAN>
    <NORTRAN>
        <NORTRAN_TRANSACTION_NO>5728</NORTRAN_TRANSACTION_NO>
        <BANNERID>HOPPA0002</BANNERID>
        <NOBTRAN_ACAT_CODE>XTELE</NOBTRAN_ACAT_CODE>
        <NORTRAN_APTY_CODE>XTELE</NORTRAN_APTY_CODE>
        <NORTRAN_AUFM_CODE>PPAIDEN</NORTRAN_AUFM_CODE>
        <NORTRAN_AUBK_CODE>SPRTELE</NORTRAN_AUBK_CODE>
        <NORTRAN_AUFD_CODE>SPRTELE_COMMENT</NORTRAN_AUFD_CODE>
        <NORTRAN_APPLY_STATUS_IND>P</NORTRAN_APPLY_STATUS_IND>
        <NORTRAN_DISPLAY_SEQ_NO>10</NORTRAN_DISPLAY_SEQ_NO>
    </NORTRAN>
    <NORTRAN>
        <NORTRAN_TRANSACTION_NO>5728</NORTRAN_TRANSACTION_NO>
        <BANNERID>HOPPA0002</BANNERID>
        <NOBTRAN_ACAT_CODE>XTELE</NOBTRAN_ACAT_CODE>
        <NORTRAN_APTY_CODE>XTELE</NORTRAN_APTY_CODE>
        <NORTRAN_AUFM_CODE>PPAIDEN</NORTRAN_AUFM_CODE>
        <NORTRAN_AUBK_CODE>SPRTELE</NORTRAN_AUBK_CODE>
        <NORTRAN_AUFD_CODE>SPRTELE_CTRY_CODE_PHONE</NORTRAN_AUFD_CODE>
        <NORTRAN_VALUE>001</NORTRAN_VALUE>
        <NORTRAN_APPLY_STATUS_IND>P</NORTRAN_APPLY_STATUS_IND>
        <NORTRAN_DISPLAY_SEQ_NO>5.5</NORTRAN_DISPLAY_SEQ_NO>
    </NORTRAN>
    <NORTRAN>
        <NORTRAN_TRANSACTION_NO>5728</NORTRAN_TRANSACTION_NO>
        <BANNERID>HOPPA0002</BANNERID>
        <NOBTRAN_ACAT_CODE>XTELE</NOBTRAN_ACAT_CODE>
        <NORTRAN_APTY_CODE>XTELE</NORTRAN_APTY_CODE>
        <NORTRAN_AUFM_CODE>PPAIDEN</NORTRAN_AUFM_CODE>
        <NORTRAN_AUBK_CODE>SPRTELE</NORTRAN_AUBK_CODE>
        <NORTRAN_AUFD_CODE>SPRTELE_INTL_ACCESS</NORTRAN_AUFD_CODE>
        <NORTRAN_APPLY_STATUS_IND>P</NORTRAN_APPLY_STATUS_IND>
        <NORTRAN_DISPLAY_SEQ_NO>6</NORTRAN_DISPLAY_SEQ_NO>
    </NORTRAN>
    <NORTRAN>
        <NORTRAN_TRANSACTION_NO>5728</NORTRAN_TRANSACTION_NO>
        <BANNERID>HOPPA0002</BANNERID>
        <NOBTRAN_ACAT_CODE>XTELE</NOBTRAN_ACAT_CODE>
        <NORTRAN_APTY_CODE>XTELE</NORTRAN_APTY_CODE>
        <NORTRAN_AUFM_CODE>PPAIDEN</NORTRAN_AUFM_CODE>
        <NORTRAN_AUBK_CODE>SPRTELE</NORTRAN_AUBK_CODE>
        <NORTRAN_AUFD_CODE>SPRTELE_PHONE_AREA</NORTRAN_AUFD_CODE>
        <NORTRAN_VALUE>301</NORTRAN_VALUE>
        <NORTRAN_APPLY_STATUS_IND>P</NORTRAN_APPLY_STATUS_IND>
        <NORTRAN_DISPLAY_SEQ_NO>3</NORTRAN_DISPLAY_SEQ_NO>
    </NORTRAN>
    <NORTRAN>
        <NORTRAN_TRANSACTION_NO>5728</NORTRAN_TRANSACTION_NO>
        <BANNERID>HOPPA0002</BANNERID>
        <NOBTRAN_ACAT_CODE>XTELE</NOBTRAN_ACAT_CODE>
        <NORTRAN_APTY_CODE>XTELE</NORTRAN_APTY_CODE>
        <NORTRAN_AUFM_CODE>PPAIDEN</NORTRAN_AUFM_CODE>
        <NORTRAN_AUBK_CODE>SPRTELE</NORTRAN_AUBK_CODE>
        <NORTRAN_AUFD_CODE>SPRTELE_PHONE_EXT</NORTRAN_AUFD_CODE>
        <NORTRAN_APPLY_STATUS_IND>P</NORTRAN_APPLY_STATUS_IND>
        <NORTRAN_DISPLAY_SEQ_NO>5</NORTRAN_DISPLAY_SEQ_NO>
    </NORTRAN>
    <NORTRAN>
        <NORTRAN_TRANSACTION_NO>5728</NORTRAN_TRANSACTION_NO>
        <BANNERID>HOPPA0002</BANNERID>
        <NOBTRAN_ACAT_CODE>XTELE</NOBTRAN_ACAT_CODE>
        <NORTRAN_APTY_CODE>XTELE</NORTRAN_APTY_CODE>
        <NORTRAN_AUFM_CODE>PPAIDEN</NORTRAN_AUFM_CODE>
        <NORTRAN_AUBK_CODE>SPRTELE</NORTRAN_AUBK_CODE>
        <NORTRAN_AUFD_CODE>SPRTELE_PHONE_NUMBER</NORTRAN_AUFD_CODE>
        <NORTRAN_VALUE>741-1924</NORTRAN_VALUE>
        <NORTRAN_APPLY_STATUS_IND>P</NORTRAN_APPLY_STATUS_IND>
        <NORTRAN_DISPLAY_SEQ_NO>4</NORTRAN_DISPLAY_SEQ_NO>
    </NORTRAN>
    <NORTRAN>
        <NORTRAN_TRANSACTION_NO>5728</NORTRAN_TRANSACTION_NO>
        <BANNERID>HOPPA0002</BANNERID>
        <NOBTRAN_ACAT_CODE>XTELE</NOBTRAN_ACAT_CODE>
        <NORTRAN_APTY_CODE>XTELE</NORTRAN_APTY_CODE>
        <NORTRAN_AUFM_CODE>PPAIDEN</NORTRAN_AUFM_CODE>
        <NORTRAN_AUBK_CODE>SPRTELE</NORTRAN_AUBK_CODE>
        <NORTRAN_AUFD_CODE>SPRTELE_PRIMARY_IND</NORTRAN_AUFD_CODE>
        <NORTRAN_VALUE>Y</NORTRAN_VALUE>
        <NORTRAN_APPLY_STATUS_IND>P</NORTRAN_APPLY_STATUS_IND>
        <NORTRAN_DISPLAY_SEQ_NO>7</NORTRAN_DISPLAY_SEQ_NO>
    </NORTRAN>
    <NORTRAN>
        <NORTRAN_TRANSACTION_NO>5728</NORTRAN_TRANSACTION_NO>
        <BANNERID>HOPPA0002</BANNERID>
        <NOBTRAN_ACAT_CODE>XTELE</NOBTRAN_ACAT_CODE>
        <NORTRAN_APTY_CODE>XTELE</NORTRAN_APTY_CODE>
        <NORTRAN_AUFM_CODE>PPAIDEN</NORTRAN_AUFM_CODE>
        <NORTRAN_AUBK_CODE>SPRTELE</NORTRAN_AUBK_CODE>
        <NORTRAN_AUFD_CODE>SPRTELE_SEQNO</NORTRAN_AUFD_CODE>
        <NORTRAN_APPLY_STATUS_IND>P</NORTRAN_APPLY_STATUS_IND>
        <NORTRAN_DISPLAY_SEQ_NO>1.5</NORTRAN_DISPLAY_SEQ_NO>
    </NORTRAN>
    <NORTRAN>
        <NORTRAN_TRANSACTION_NO>5728</NORTRAN_TRANSACTION_NO>
        <BANNERID>HOPPA0002</BANNERID>
        <NOBTRAN_ACAT_CODE>XTELE</NOBTRAN_ACAT_CODE>
        <NORTRAN_APTY_CODE>XTELE</NORTRAN_APTY_CODE>
        <NORTRAN_AUFM_CODE>PPAIDEN</NORTRAN_AUFM_CODE>
        <NORTRAN_AUBK_CODE>SPRTELE</NORTRAN_AUBK_CODE>
        <NORTRAN_AUFD_CODE>SPRTELE_STATUS_IND</NORTRAN_AUFD_CODE>
        <NORTRAN_APPLY_STATUS_IND>P</NORTRAN_APPLY_STATUS_IND>
        <NORTRAN_DISPLAY_SEQ_NO>9</NORTRAN_DISPLAY_SEQ_NO>
    </NORTRAN>
    <NORTRAN>
        <NORTRAN_TRANSACTION_NO>5728</NORTRAN_TRANSACTION_NO>
        <BANNERID>HOPPA0002</BANNERID>
        <NOBTRAN_ACAT_CODE>XTELE</NOBTRAN_ACAT_CODE>
        <NORTRAN_APTY_CODE>XTELE</NORTRAN_APTY_CODE>
        <NORTRAN_AUFM_CODE>PPAIDEN</NORTRAN_AUFM_CODE>
        <NORTRAN_AUBK_CODE>SPRTELE</NORTRAN_AUBK_CODE>
        <NORTRAN_AUFD_CODE>SPRTELE_TELE_CODE</NORTRAN_AUFD_CODE>
        <NORTRAN_VALUE>CELL</NORTRAN_VALUE>
        <NORTRAN_APPLY_STATUS_IND>P</NORTRAN_APPLY_STATUS_IND>
        <NORTRAN_DISPLAY_SEQ_NO>1</NORTRAN_DISPLAY_SEQ_NO>
    </NORTRAN>
    <NORTRAN>
        <NORTRAN_TRANSACTION_NO>5728</NORTRAN_TRANSACTION_NO>
        <BANNERID>HOPPA0002</BANNERID>
        <NOBTRAN_ACAT_CODE>XTELE</NOBTRAN_ACAT_CODE>
        <NORTRAN_APTY_CODE>XTELE</NORTRAN_APTY_CODE>
        <NORTRAN_AUFM_CODE>PPAIDEN</NORTRAN_AUFM_CODE>
        <NORTRAN_AUBK_CODE>SPRTELE</NORTRAN_AUBK_CODE>
        <NORTRAN_AUFD_CODE>SPRTELE_UNLIST_IND</NORTRAN_AUFD_CODE>
        <NORTRAN_APPLY_STATUS_IND>P</NORTRAN_APPLY_STATUS_IND>
        <NORTRAN_DISPLAY_SEQ_NO>8</NORTRAN_DISPLAY_SEQ_NO>
    </NORTRAN>
    <NORTRAN>
        <NORTRAN_TRANSACTION_NO>5729</NORTRAN_TRANSACTION_NO>
        <BANNERID>HOPPA0003</BANNERID>
        <NOBTRAN_ACAT_CODE>XADTEL</NOBTRAN_ACAT_CODE>
        <NORTRAN_APTY_CODE>XADTEL</NORTRAN_APTY_CODE>
        <NORTRAN_AUFM_CODE>PPAIDEN</NORTRAN_AUFM_CODE>
        <NORTRAN_AUBK_CODE>SPRADDR</NORTRAN_AUBK_CODE>
        <NORTRAN_AUFD_CODE>SPRADDR_ATYP_CODE</NORTRAN_AUFD_CODE>
        <NORTRAN_VALUE>PR</NORTRAN_VALUE>
        <NORTRAN_APPLY_STATUS_IND>P</NORTRAN_APPLY_STATUS_IND>
        <NORTRAN_DISPLAY_SEQ_NO>4</NORTRAN_DISPLAY_SEQ_NO>
    </NORTRAN>
    <NORTRAN>
        <NORTRAN_TRANSACTION_NO>5729</NORTRAN_TRANSACTION_NO>
        <BANNERID>HOPPA0003</BANNERID>
        <NOBTRAN_ACAT_CODE>XADTEL</NOBTRAN_ACAT_CODE>
        <NORTRAN_APTY_CODE>XADTEL</NORTRAN_APTY_CODE>
        <NORTRAN_AUFM_CODE>PPAIDEN</NORTRAN_AUFM_CODE>
        <NORTRAN_AUBK_CODE>SPRADDR</NORTRAN_AUBK_CODE>
        <NORTRAN_AUFD_CODE>SPRADDR_CITY</NORTRAN_AUFD_CODE>
        <NORTRAN_APPLY_STATUS_IND>P</NORTRAN_APPLY_STATUS_IND>
        <NORTRAN_DISPLAY_SEQ_NO>8</NORTRAN_DISPLAY_SEQ_NO>
    </NORTRAN>
    <NORTRAN>
        <NORTRAN_TRANSACTION_NO>5729</NORTRAN_TRANSACTION_NO>
        <BANNERID>HOPPA0003</BANNERID>
        <NOBTRAN_ACAT_CODE>XADTEL</NOBTRAN_ACAT_CODE>
        <NORTRAN_APTY_CODE>XADTEL</NORTRAN_APTY_CODE>
        <NORTRAN_AUFM_CODE>PPAIDEN</NORTRAN_AUFM_CODE>
        <NORTRAN_AUBK_CODE>SPRADDR</NORTRAN_AUBK_CODE>
        <NORTRAN_AUFD_CODE>SPRADDR_FROM_DATE</NORTRAN_AUFD_CODE>
        <NORTRAN_APPLY_STATUS_IND>P</NORTRAN_APPLY_STATUS_IND>
        <NORTRAN_DISPLAY_SEQ_NO>1</NORTRAN_DISPLAY_SEQ_NO>
    </NORTRAN>
    <NORTRAN>
        <NORTRAN_TRANSACTION_NO>5729</NORTRAN_TRANSACTION_NO>
        <BANNERID>HOPPA0003</BANNERID>
        <NOBTRAN_ACAT_CODE>XADTEL</NOBTRAN_ACAT_CODE>
        <NORTRAN_APTY_CODE>XADTEL</NORTRAN_APTY_CODE>
        <NORTRAN_AUFM_CODE>PPAIDEN</NORTRAN_AUFM_CODE>
        <NORTRAN_AUBK_CODE>SPRADDR</NORTRAN_AUBK_CODE>
        <NORTRAN_AUFD_CODE>SPRADDR_SEQNO</NORTRAN_AUFD_CODE>
        <NORTRAN_VALUE>1</NORTRAN_VALUE>
        <NORTRAN_APPLY_STATUS_IND>P</NORTRAN_APPLY_STATUS_IND>
        <NORTRAN_DISPLAY_SEQ_NO>3</NORTRAN_DISPLAY_SEQ_NO>
    </NORTRAN>
    <NORTRAN>
        <NORTRAN_TRANSACTION_NO>5729</NORTRAN_TRANSACTION_NO>
        <BANNERID>HOPPA0003</BANNERID>
        <NOBTRAN_ACAT_CODE>XADTEL</NOBTRAN_ACAT_CODE>
        <NORTRAN_APTY_CODE>XADTEL</NORTRAN_APTY_CODE>
        <NORTRAN_AUFM_CODE>PPAIDEN</NORTRAN_AUFM_CODE>
        <NORTRAN_AUBK_CODE>SPRADDR</NORTRAN_AUBK_CODE>
        <NORTRAN_AUFD_CODE>SPRADDR_STAT_CODE</NORTRAN_AUFD_CODE>
        <NORTRAN_APPLY_STATUS_IND>P</NORTRAN_APPLY_STATUS_IND>
        <NORTRAN_DISPLAY_SEQ_NO>9</NORTRAN_DISPLAY_SEQ_NO>
    </NORTRAN>
    <NORTRAN>
        <NORTRAN_TRANSACTION_NO>5729</NORTRAN_TRANSACTION_NO>
        <BANNERID>HOPPA0003</BANNERID>
        <NOBTRAN_ACAT_CODE>XADTEL</NOBTRAN_ACAT_CODE>
        <NORTRAN_APTY_CODE>XADTEL</NORTRAN_APTY_CODE>
        <NORTRAN_AUFM_CODE>PPAIDEN</NORTRAN_AUFM_CODE>
        <NORTRAN_AUBK_CODE>SPRADDR</NORTRAN_AUBK_CODE>
        <NORTRAN_AUFD_CODE>SPRADDR_STREET_LINE1</NORTRAN_AUFD_CODE>
        <NORTRAN_APPLY_STATUS_IND>P</NORTRAN_APPLY_STATUS_IND>
        <NORTRAN_DISPLAY_SEQ_NO>5</NORTRAN_DISPLAY_SEQ_NO>
    </NORTRAN>
    <NORTRAN>
        <NORTRAN_TRANSACTION_NO>5729</NORTRAN_TRANSACTION_NO>
        <BANNERID>HOPPA0003</BANNERID>
        <NOBTRAN_ACAT_CODE>XADTEL</NOBTRAN_ACAT_CODE>
        <NORTRAN_APTY_CODE>XADTEL</NORTRAN_APTY_CODE>
        <NORTRAN_AUFM_CODE>PPAIDEN</NORTRAN_AUFM_CODE>
        <NORTRAN_AUBK_CODE>SPRADDR</NORTRAN_AUBK_CODE>
        <NORTRAN_AUFD_CODE>SPRADDR_STREET_LINE2</NORTRAN_AUFD_CODE>
        <NORTRAN_APPLY_STATUS_IND>P</NORTRAN_APPLY_STATUS_IND>
        <NORTRAN_DISPLAY_SEQ_NO>6</NORTRAN_DISPLAY_SEQ_NO>
    </NORTRAN>
    <NORTRAN>
        <NORTRAN_TRANSACTION_NO>5729</NORTRAN_TRANSACTION_NO>
        <BANNERID>HOPPA0003</BANNERID>
        <NOBTRAN_ACAT_CODE>XADTEL</NOBTRAN_ACAT_CODE>
        <NORTRAN_APTY_CODE>XADTEL</NORTRAN_APTY_CODE>
        <NORTRAN_AUFM_CODE>PPAIDEN</NORTRAN_AUFM_CODE>
        <NORTRAN_AUBK_CODE>SPRADDR</NORTRAN_AUBK_CODE>
        <NORTRAN_AUFD_CODE>SPRADDR_STREET_LINE3</NORTRAN_AUFD_CODE>
        <NORTRAN_APPLY_STATUS_IND>P</NORTRAN_APPLY_STATUS_IND>
        <NORTRAN_DISPLAY_SEQ_NO>7</NORTRAN_DISPLAY_SEQ_NO>
    </NORTRAN>
    <NORTRAN>
        <NORTRAN_TRANSACTION_NO>5729</NORTRAN_TRANSACTION_NO>
        <BANNERID>HOPPA0003</BANNERID>
        <NOBTRAN_ACAT_CODE>XADTEL</NOBTRAN_ACAT_CODE>
        <NORTRAN_APTY_CODE>XADTEL</NORTRAN_APTY_CODE>
        <NORTRAN_AUFM_CODE>PPAIDEN</NORTRAN_AUFM_CODE>
        <NORTRAN_AUBK_CODE>SPRADDR</NORTRAN_AUBK_CODE>
        <NORTRAN_AUFD_CODE>SPRADDR_TO_DATE</NORTRAN_AUFD_CODE>
        <NORTRAN_APPLY_STATUS_IND>P</NORTRAN_APPLY_STATUS_IND>
        <NORTRAN_DISPLAY_SEQ_NO>2</NORTRAN_DISPLAY_SEQ_NO>
    </NORTRAN>
    <NORTRAN>
        <NORTRAN_TRANSACTION_NO>5729</NORTRAN_TRANSACTION_NO>
        <BANNERID>HOPPA0003</BANNERID>
        <NOBTRAN_ACAT_CODE>XADTEL</NOBTRAN_ACAT_CODE>
        <NORTRAN_APTY_CODE>XADTEL</NORTRAN_APTY_CODE>
        <NORTRAN_AUFM_CODE>PPAIDEN</NORTRAN_AUFM_CODE>
        <NORTRAN_AUBK_CODE>SPRADDR</NORTRAN_AUBK_CODE>
        <NORTRAN_AUFD_CODE>SPRADDR_ZIP</NORTRAN_AUFD_CODE>
        <NORTRAN_APPLY_STATUS_IND>P</NORTRAN_APPLY_STATUS_IND>
        <NORTRAN_DISPLAY_SEQ_NO>10</NORTRAN_DISPLAY_SEQ_NO>
    </NORTRAN>
    <NORTRAN>
        <NORTRAN_TRANSACTION_NO>5729</NORTRAN_TRANSACTION_NO>
        <BANNERID>HOPPA0003</BANNERID>
        <NOBTRAN_ACAT_CODE>XADTEL</NOBTRAN_ACAT_CODE>
        <NORTRAN_APTY_CODE>XADTEL</NORTRAN_APTY_CODE>
        <NORTRAN_AUFM_CODE>PPAIDEN</NORTRAN_AUFM_CODE>
        <NORTRAN_AUBK_CODE>SPRTELE</NORTRAN_AUBK_CODE>
        <NORTRAN_AUFD_CODE>SPRTELE_ADDR_SEQNO</NORTRAN_AUFD_CODE>
        <NORTRAN_APPLY_STATUS_IND>P</NORTRAN_APPLY_STATUS_IND>
        <NORTRAN_DISPLAY_SEQ_NO>13</NORTRAN_DISPLAY_SEQ_NO>
    </NORTRAN>
    <NORTRAN>
        <NORTRAN_TRANSACTION_NO>5729</NORTRAN_TRANSACTION_NO>
        <BANNERID>HOPPA0003</BANNERID>
        <NOBTRAN_ACAT_CODE>XADTEL</NOBTRAN_ACAT_CODE>
        <NORTRAN_APTY_CODE>XADTEL</NORTRAN_APTY_CODE>
        <NORTRAN_AUFM_CODE>PPAIDEN</NORTRAN_AUFM_CODE>
        <NORTRAN_AUBK_CODE>SPRTELE</NORTRAN_AUBK_CODE>
        <NORTRAN_AUFD_CODE>SPRTELE_ATYP_CODE</NORTRAN_AUFD_CODE>
        <NORTRAN_APPLY_STATUS_IND>P</NORTRAN_APPLY_STATUS_IND>
        <NORTRAN_DISPLAY_SEQ_NO>12</NORTRAN_DISPLAY_SEQ_NO>
    </NORTRAN>
    <NORTRAN>
        <NORTRAN_TRANSACTION_NO>5729</NORTRAN_TRANSACTION_NO>
        <BANNERID>HOPPA0003</BANNERID>
        <NOBTRAN_ACAT_CODE>XADTEL</NOBTRAN_ACAT_CODE>
        <NORTRAN_APTY_CODE>XADTEL</NORTRAN_APTY_CODE>
        <NORTRAN_AUFM_CODE>PPAIDEN</NORTRAN_AUFM_CODE>
        <NORTRAN_AUBK_CODE>SPRTELE</NORTRAN_AUBK_CODE>
        <NORTRAN_AUFD_CODE>SPRTELE_PHONE_AREA</NORTRAN_AUFD_CODE>
        <NORTRAN_VALUE>956</NORTRAN_VALUE>
        <NORTRAN_APPLY_STATUS_IND>P</NORTRAN_APPLY_STATUS_IND>
        <NORTRAN_DISPLAY_SEQ_NO>17</NORTRAN_DISPLAY_SEQ_NO>
    </NORTRAN>
    <NORTRAN>
        <NORTRAN_TRANSACTION_NO>5729</NORTRAN_TRANSACTION_NO>
        <BANNERID>HOPPA0003</BANNERID>
        <NOBTRAN_ACAT_CODE>XADTEL</NOBTRAN_ACAT_CODE>
        <NORTRAN_APTY_CODE>XADTEL</NORTRAN_APTY_CODE>
        <NORTRAN_AUFM_CODE>PPAIDEN</NORTRAN_AUFM_CODE>
        <NORTRAN_AUBK_CODE>SPRTELE</NORTRAN_AUBK_CODE>
        <NORTRAN_AUFD_CODE>SPRTELE_PHONE_EXT</NORTRAN_AUFD_CODE>
        <NORTRAN_APPLY_STATUS_IND>P</NORTRAN_APPLY_STATUS_IND>
        <NORTRAN_DISPLAY_SEQ_NO>19</NORTRAN_DISPLAY_SEQ_NO>
    </NORTRAN>
    <NORTRAN>
        <NORTRAN_TRANSACTION_NO>5729</NORTRAN_TRANSACTION_NO>
        <BANNERID>HOPPA0003</BANNERID>
        <NOBTRAN_ACAT_CODE>XADTEL</NOBTRAN_ACAT_CODE>
        <NORTRAN_APTY_CODE>XADTEL</NORTRAN_APTY_CODE>
        <NORTRAN_AUFM_CODE>PPAIDEN</NORTRAN_AUFM_CODE>
        <NORTRAN_AUBK_CODE>SPRTELE</NORTRAN_AUBK_CODE>
        <NORTRAN_AUFD_CODE>SPRTELE_PHONE_NUMBER</NORTRAN_AUFD_CODE>
        <NORTRAN_VALUE>484-8119</NORTRAN_VALUE>
        <NORTRAN_APPLY_STATUS_IND>P</NORTRAN_APPLY_STATUS_IND>
        <NORTRAN_DISPLAY_SEQ_NO>18</NORTRAN_DISPLAY_SEQ_NO>
    </NORTRAN>
    <NORTRAN>
        <NORTRAN_TRANSACTION_NO>5729</NORTRAN_TRANSACTION_NO>
        <BANNERID>HOPPA0003</BANNERID>
        <NOBTRAN_ACAT_CODE>XADTEL</NOBTRAN_ACAT_CODE>
        <NORTRAN_APTY_CODE>XADTEL</NORTRAN_APTY_CODE>
        <NORTRAN_AUFM_CODE>PPAIDEN</NORTRAN_AUFM_CODE>
        <NORTRAN_AUBK_CODE>SPRTELE</NORTRAN_AUBK_CODE>
        <NORTRAN_AUFD_CODE>SPRTELE_SEQNO</NORTRAN_AUFD_CODE>
        <NORTRAN_APPLY_STATUS_IND>P</NORTRAN_APPLY_STATUS_IND>
        <NORTRAN_DISPLAY_SEQ_NO>15</NORTRAN_DISPLAY_SEQ_NO>
    </NORTRAN>
    <NORTRAN>
        <NORTRAN_TRANSACTION_NO>5729</NORTRAN_TRANSACTION_NO>
        <BANNERID>HOPPA0003</BANNERID>
        <NOBTRAN_ACAT_CODE>XADTEL</NOBTRAN_ACAT_CODE>
        <NORTRAN_APTY_CODE>XADTEL</NORTRAN_APTY_CODE>
        <NORTRAN_AUFM_CODE>PPAIDEN</NORTRAN_AUFM_CODE>
        <NORTRAN_AUBK_CODE>SPRTELE</NORTRAN_AUBK_CODE>
        <NORTRAN_AUFD_CODE>SPRTELE_TELE_CODE</NORTRAN_AUFD_CODE>
        <NORTRAN_VALUE>PR</NORTRAN_VALUE>
        <NORTRAN_APPLY_STATUS_IND>P</NORTRAN_APPLY_STATUS_IND>
        <NORTRAN_DISPLAY_SEQ_NO>14</NORTRAN_DISPLAY_SEQ_NO>
    </NORTRAN>

    <NORROUT>
        <NORROUT_TRANSACTION_NO>5727</NORROUT_TRANSACTION_NO>
        <BANNERID>HOPPA0001</BANNERID>
        <NOBTRAN_ACAT_CODE>XTELE</NOBTRAN_ACAT_CODE>
        <NORROUT_RECIPIENT_USER_ID>PA00016</NORROUT_RECIPIENT_USER_ID>
        <NORROUT_ALVL_CODE>SUPER</NORROUT_ALVL_CODE>
        <NORROUT_ACTION_IND>L</NORROUT_ACTION_IND>
        <NORROUT_QUEUE_STATUS_IND>I</NORROUT_QUEUE_STATUS_IND>
        <NORROUT_STATUS_DATE_TIME>03/01/2020</NORROUT_STATUS_DATE_TIME>
        <NORROUT_LEVEL_NO>99</NORROUT_LEVEL_NO>
    </NORROUT>
    <NORROUT>
        <NORROUT_TRANSACTION_NO>5728</NORROUT_TRANSACTION_NO>
        <BANNERID>HOPPA0002</BANNERID>
        <NOBTRAN_ACAT_CODE>XTELE</NOBTRAN_ACAT_CODE>
        <NORROUT_RECIPIENT_USER_ID>PA00016</NORROUT_RECIPIENT_USER_ID>
        <NORROUT_ALVL_CODE>SUPER</NORROUT_ALVL_CODE>
        <NORROUT_ACTION_IND>L</NORROUT_ACTION_IND>
        <NORROUT_QUEUE_STATUS_IND>P</NORROUT_QUEUE_STATUS_IND>
        <NORROUT_STATUS_DATE_TIME>03/01/2020</NORROUT_STATUS_DATE_TIME>
        <NORROUT_LEVEL_NO>99</NORROUT_LEVEL_NO>
    </NORROUT>
    <NORROUT>
        <NORROUT_TRANSACTION_NO>5729</NORROUT_TRANSACTION_NO>
        <BANNERID>HOPPA0003</BANNERID>
        <NOBTRAN_ACAT_CODE>XADTEL</NOBTRAN_ACAT_CODE>
        <NORROUT_RECIPIENT_USER_ID>PA00016</NORROUT_RECIPIENT_USER_ID>
        <NORROUT_ALVL_CODE>SUPER</NORROUT_ALVL_CODE>
        <NORROUT_ACTION_IND>L</NORROUT_ACTION_IND>
        <NORROUT_QUEUE_STATUS_IND>I</NORROUT_QUEUE_STATUS_IND>
        <NORROUT_STATUS_DATE_TIME>03/01/2020</NORROUT_STATUS_DATE_TIME>
        <NORROUT_LEVEL_NO>99</NORROUT_LEVEL_NO>
    </NORROUT>
    <NORROUT>
        <NORROUT_TRANSACTION_NO>5729</NORROUT_TRANSACTION_NO>
        <BANNERID>HOPPA0003</BANNERID>
        <NOBTRAN_ACAT_CODE>XADTEL</NOBTRAN_ACAT_CODE>
        <NORROUT_RECIPIENT_USER_ID>PA00010</NORROUT_RECIPIENT_USER_ID>
        <NORROUT_ALVL_CODE>MANGR</NORROUT_ALVL_CODE>
        <NORROUT_ACTION_IND>A</NORROUT_ACTION_IND>
        <NORROUT_QUEUE_STATUS_IND>P</NORROUT_QUEUE_STATUS_IND>
        <NORROUT_STATUS_DATE_TIME>03/01/2020</NORROUT_STATUS_DATE_TIME>
        <NORROUT_LEVEL_NO>35</NORROUT_LEVEL_NO>
    </NORROUT>

</EPAF_DATA>