<?xml version="1.0" encoding="Windows-1252" ?>
<!-- *****************************************************************************
Copyright 2010-2013 Ellucian Company L.P. and its affiliates.
 ********************************************************************************* -->
<CATALOG>
    <SCRCORQ>
        <SCRCORQ_SUBJ_CODE>LISK</SCRCORQ_SUBJ_CODE>
        <SCRCORQ_CRSE_NUMB>401</SCRCORQ_CRSE_NUMB>
        <DELETE>YES</DELETE>
    </SCRCORQ>
    <SCREQIV>
        <SCREQIV_SUBJ_CODE>LISK</SCREQIV_SUBJ_CODE>
        <SCREQIV_CRSE_NUMB>401</SCREQIV_CRSE_NUMB>
        <DELETE>YES</DELETE>
    </SCREQIV>
    <SCRFEES>
        <SCRFEES_SUBJ_CODE>LISK</SCRFEES_SUBJ_CODE>
        <SCRFEES_CRSE_NUMB>401</SCRFEES_CRSE_NUMB>
        <DELETE>YES</DELETE>
    </SCRFEES>
    <SCRATTR>
        <SCRATTR_SUBJ_CODE>LISK</SCRATTR_SUBJ_CODE>
        <SCRATTR_CRSE_NUMB>401</SCRATTR_CRSE_NUMB>
        <DELETE>YES</DELETE>
    </SCRATTR>
    <SCRSBGI>
        <SCRSBGI_SUBJ_CODE>LISK</SCRSBGI_SUBJ_CODE>
        <SCRSBGI_CRSE_NUMB>401</SCRSBGI_CRSE_NUMB>
        <DELETE>YES</DELETE>
    </SCRSBGI>
     <SCBSUPP>
        <SCBSUPP_SUBJ_CODE>LISK</SCBSUPP_SUBJ_CODE>
        <SCBSUPP_CRSE_NUMB>401</SCBSUPP_CRSE_NUMB>
        <DELETE>YES</DELETE>
    </SCBSUPP>
    <SCBDESC>
        <SCBDESC_SUBJ_CODE>LISK</SCBDESC_SUBJ_CODE>
        <SCBDESC_CRSE_NUMB>401</SCBDESC_CRSE_NUMB>
        <DELETE>YES</DELETE>
    </SCBDESC>
    <SCRTEXT>
        <SCRTEXT_SUBJ_CODE>LISK</SCRTEXT_SUBJ_CODE>
        <SCRTEXT_CRSE_NUMB>401</SCRTEXT_CRSE_NUMB>
        <DELETE>YES</DELETE>
    </SCRTEXT>
    <SV_SCRINTG>
        <SCRINTG_SUBJ_CODE>LISK</SCRINTG_SUBJ_CODE>
        <SCRINTG_CRSE_NUMB>401</SCRINTG_CRSE_NUMB>
        <DELETE>YES</DELETE>
    </SV_SCRINTG>
    <SCRCORQ>
        <SCRCORQ_SUBJ_CODE>LISK</SCRCORQ_SUBJ_CODE>
        <SCRCORQ_CRSE_NUMB>402</SCRCORQ_CRSE_NUMB>
        <DELETE>YES</DELETE>
    </SCRCORQ>
    <SCREQIV>
        <SCREQIV_SUBJ_CODE>LISK</SCREQIV_SUBJ_CODE>
        <SCREQIV_CRSE_NUMB>402</SCREQIV_CRSE_NUMB>
        <DELETE>YES</DELETE>
    </SCREQIV>
    <SCRFEES>
        <SCRFEES_SUBJ_CODE>LISK</SCRFEES_SUBJ_CODE>
        <SCRFEES_CRSE_NUMB>402</SCRFEES_CRSE_NUMB>
        <DELETE>YES</DELETE>
    </SCRFEES>
    <SCRATTR>
        <SCRATTR_SUBJ_CODE>LISK</SCRATTR_SUBJ_CODE>
        <SCRATTR_CRSE_NUMB>402</SCRATTR_CRSE_NUMB>
        <DELETE>YES</DELETE>
    </SCRATTR>
    <SCRSBGI>
        <SCRSBGI_SUBJ_CODE>LISK</SCRSBGI_SUBJ_CODE>
        <SCRSBGI_CRSE_NUMB>402</SCRSBGI_CRSE_NUMB>
        <DELETE>YES</DELETE>
    </SCRSBGI>
    <SCBSUPP>
        <SCBSUPP_SUBJ_CODE>LISK</SCBSUPP_SUBJ_CODE>
        <SCBSUPP_CRSE_NUMB>402</SCBSUPP_CRSE_NUMB>
        <DELETE>YES</DELETE>
    </SCBSUPP>
    <SCBDESC>
        <SCBDESC_SUBJ_CODE>LISK</SCBDESC_SUBJ_CODE>
        <SCBDESC_CRSE_NUMB>402</SCBDESC_CRSE_NUMB>
        <DELETE>YES</DELETE>
    </SCBDESC>
    <SCRTEXT>
        <SCRTEXT_SUBJ_CODE>LISK</SCRTEXT_SUBJ_CODE>
        <SCRTEXT_CRSE_NUMB>402</SCRTEXT_CRSE_NUMB>
        <DELETE>YES</DELETE>
    </SCRTEXT>
    <SV_SCRINTG>
        <SCRINTG_SUBJ_CODE>LISK</SCRINTG_SUBJ_CODE>
        <SCRINTG_CRSE_NUMB>402</SCRINTG_CRSE_NUMB>
        <DELETE>YES</DELETE>
    </SV_SCRINTG>
</CATALOG>