<?xml version="1.0" encoding="Windows-1252" ?>
<!-- *****************************************************************************
Copyright 2016 Ellucian Company L.P. and its affiliates.
 ********************************************************************************* -->
<FGBTRNH>
    <FGBTRNH>
        <FGBTRNH_ACTIVITY_DATE>01-01-2016</FGBTRNH_ACTIVITY_DATE>
        <FGBTRNH_DOC_CODE>DCITTST</FGBTRNH_DOC_CODE>
        <FGBTRNH_DOC_SEQ_CODE>20</FGBTRNH_DOC_SEQ_CODE>
        <FGBTRNH_DR_CR_IND>D</FGBTRNH_DR_CR_IND>
        <FGBTRNH_ITEM_NUM>1</FGBTRNH_ITEM_NUM>
        <FGBTRNH_REVERSAL_IND>Y</FGBTRNH_REVERSAL_IND>
        <FGBTRNH_RUCL_CODE>RC</FGBTRNH_RUCL_CODE>
        <FGBTRNH_SEQ_NUM>1</FGBTRNH_SEQ_NUM>
        <FGBTRNH_SERIAL_NUM>1</FGBTRNH_SERIAL_NUM>
        <FGBTRNH_SUBMISSION_NUMBER>1</FGBTRNH_SUBMISSION_NUMBER>
        <FGBTRNH_TRANS_AMT>100.00</FGBTRNH_TRANS_AMT>
        <FGBTRNH_TRANS_DATE>01-01-9999</FGBTRNH_TRANS_DATE>
        <FGBTRNH_USER_ID>USR_ID</FGBTRNH_USER_ID>
        <FGBTRNH_DATA_ORIGIN>GRAILS</FGBTRNH_DATA_ORIGIN>
    </FGBTRNH>
</FGBTRNH>
