<?xml version="1.0" encoding="Windows-1252" ?>
<!-- *****************************************************************************
Copyright 2017 Ellucian Company L.P. and its affiliates.
 ********************************************************************************* -->
<TERM>
    <SFRRSTS>
        <SFRRSTS_TERM_CODE>201410</SFRRSTS_TERM_CODE>
        <SFRRSTS_PTRM_CODE>1</SFRRSTS_PTRM_CODE>
        <SFRRSTS_RSTS_CODE>RW</SFRRSTS_RSTS_CODE>
        <SFRRSTS_START_DATE>01-AUG-2010</SFRRSTS_START_DATE>
        <SFRRSTS_END_DATE>31-DEC-2023</SFRRSTS_END_DATE>
        <SFRRSTS_EFF_BY_ENRL_STAT>Y</SFRRSTS_EFF_BY_ENRL_STAT>
        <SFRRSTS_ACTIVITY_DATE>01-JAN-2010</SFRRSTS_ACTIVITY_DATE>
        <SFRRSTS_VR_ELIG_IND>N</SFRRSTS_VR_ELIG_IND>
        <SFRRSTS_USER_ID>GRAILS</SFRRSTS_USER_ID>
        <SFRRSTS_DATA_ORIGIN>GRAILS</SFRRSTS_DATA_ORIGIN>
    </SFRRSTS>
</TERM>